Semester_5/Course_work/Root_calculator/src/src_logic/data_transmitter.v
module data_transmitter(
    input clk,
    input [31:0] in_data,
    input in_data_ready,
	 input data_request,
    output reg [7:0] out_data,
    output reg out_data_ready
);

    reg [1:0] byte_counter;
	 reg [31:0] in_data_reg;
	 
    initial begin
        byte_counter = 0;
		  out_data = 0;
		  out_data_ready = 0;
    end

    always @(posedge clk) begin
		  if(out_data_ready == 1'b1)
			out_data_ready <= 1'b0;
        if(data_request == 1'b1) begin
            case (byte_counter)
                2'b00: begin
                    out_data <= in_data_reg[31:24];
                    byte_counter = byte_counter + 1'b1;
                    out_data_ready <= 1'b1;
                end 
                2'b01: begin
                    out_data <= in_data_reg[23:16];
                    byte_counter = byte_counter + 1'b1;
						  out_data_ready <= 1'b1;
                end 
                2'b10: begin
                    out_data <= in_data_reg[15:8];
                    byte_counter = byte_counter + 1'b1;
						  out_data_ready <= 1'b1;
                end 
                2'b11: begin
                    out_data <= in_data_reg[7:0];
                    byte_counter = byte_counter + 1'b1;
                    out_data_ready <= 1'b1;
                end
            endcase
        end
		  if(in_data_ready == 1'b1) begin
			  in_data_reg <= in_data;
		  end
    end
	 
endmodule

Semester_5/Course_work/Root_calculator/src/src_testbenches/data_transmitter_testbench.v
`include "../src_logic/data_transmitter.v"

`timescale 1ns/1ps

module data_transmitter_testbench;

    reg clk;
    reg [31:0] in_data;
    reg in_data_ready;
	 reg data_request;
    wire [7:0] out_data;
    wire out_data_ready;

    data_transmitter dut(
        .clk(clk),
        .in_data(in_data),
		  .data_request(data_request),
        .in_data_ready(in_data_ready),
        .out_data(out_data),
        .out_data_ready(out_data_ready)
    );

    initial begin
        {clk, in_data, in_data_ready} = 0;
    end

    always #5 clk = ~clk;

    initial begin
        
        $dumpfile("data_transmitter_testbench.vcd");
        $dumpvars;

		  #15 
		  
		  in_data_ready = 1;
		  
        #5
        in_data = 32'd10208854;
       
        #15
		  
		  data_request = 1;
		  
		  #20
		  
		  data_request = 0;
		  
		  #35 
		  
		  data_request = 1;

		  #10
		  
		  data_request = 0;
		  
        #70

        $stop;
        $finish;

    end

endmodule

Semester_5/Course_work/Root_calculator/quartus/simulation/modelsim/data_transmitter_testbench.vcd
$date
	Fri Dec 16 11:11:59 2022
$end
$version
	Questa Intel Starter FPGA Edition Version 2021.2
$end
$timescale
	1ps
$end

$scope module data_transmitter_testbench $end
$var reg 1 ! clk $end
$var reg 32 " in_data [31:0] $end
$var reg 1 # in_data_ready $end
$var reg 1 $ data_request $end
$var wire 1 % out_data [7] $end
$var wire 1 & out_data [6] $end
$var wire 1 ' out_data [5] $end
$var wire 1 ( out_data [4] $end
$var wire 1 ) out_data [3] $end
$var wire 1 * out_data [2] $end
$var wire 1 + out_data [1] $end
$var wire 1 , out_data [0] $end
$var wire 1 - out_data_ready $end

$scope module dut $end
$var wire 1 . clk $end
$var wire 1 / in_data [31] $end
$var wire 1 0 in_data [30] $end
$var wire 1 1 in_data [29] $end
$var wire 1 2 in_data [28] $end
$var wire 1 3 in_data [27] $end
$var wire 1 4 in_data [26] $end
$var wire 1 5 in_data [25] $end
$var wire 1 6 in_data [24] $end
$var wire 1 7 in_data [23] $end
$var wire 1 8 in_data [22] $end
$var wire 1 9 in_data [21] $end
$var wire 1 : in_data [20] $end
$var wire 1 ; in_data [19] $end
$var wire 1 < in_data [18] $end
$var wire 1 = in_data [17] $end
$var wire 1 > in_data [16] $end
$var wire 1 ? in_data [15] $end
$var wire 1 @ in_data [14] $end
$var wire 1 A in_data [13] $end
$var wire 1 B in_data [12] $end
$var wire 1 C in_data [11] $end
$var wire 1 D in_data [10] $end
$var wire 1 E in_data [9] $end
$var wire 1 F in_data [8] $end
$var wire 1 G in_data [7] $end
$var wire 1 H in_data [6] $end
$var wire 1 I in_data [5] $end
$var wire 1 J in_data [4] $end
$var wire 1 K in_data [3] $end
$var wire 1 L in_data [2] $end
$var wire 1 M in_data [1] $end
$var wire 1 N in_data [0] $end
$var wire 1 O in_data_ready $end
$var wire 1 P data_request $end
$var reg 8 Q out_data [7:0] $end
$var reg 1 R out_data_ready $end
$var reg 2 S byte_counter [1:0] $end
$var reg 32 T in_data_reg [31:0] $end
$upscope $end
$upscope $end
$enddefinitions $end
#0
$dumpvars
0!
b0 "
0#
x$
b0 Q
0R
b0 S
bx T
0,
0+
0*
0)
0(
0'
0&
0%
0-
xP
0O
0N
0M
0L
0K
0J
0I
0H
0G
0F
0E
0D
0C
0B
0A
0@
0?
0>
0=
0<
0;
0:
09
08
07
06
05
04
03
02
01
00
0/
0.
$end
#5000
1!
1.
#10000
0!
0.
#15000
1#
1!
1O
1.
b0 T
#20000
b100110111100011001010110 "
0!
1M
1L
1J
1H
1E
1D
1@
1?
1>
1=
1;
1:
17
0.
#25000
1!
1.
b100110111100011001010110 T
#30000
0!
0.
#35000
1$
1!
1P
1.
b1 S
1R
1-
#40000
0!
0.
#45000
1!
1.
b10 S
0R
b10011011 Q
1R
1,
1+
1)
1(
1%
#50000
0!
0.
#55000
0$
1!
0P
1.
0R
0-
#60000
0!
0.
#65000
1!
1.
#70000
0!
0.
#75000
1!
1.
#80000
0!
0.
#85000
1!
1.
#90000
1$
0!
1P
0.
#95000
1!
1.
b11 S
b11000110 Q
1R
0,
1*
0)
0(
1&
1-
#100000
0$
0!
0P
0.
#105000
1!
1.
0R
0-
