Semester_5/Course_work/Root_calculator/src/src_logic/RS232_transmitter.v
module RS232_transmitter #(
    parameter CLK_DIVIDER = 5208 // 9600 baud
)(
    input clk,
    input [7:0] data,
    input data_ready,
    output reg tx,
    output reg rts
);

    localparam Wait_st = 2'b00;
    localparam Start_st = 2'b01;
    localparam Data_st = 2'b10;
    localparam Stop_st = 2'b11;

    reg [1:0] cur_state;
    reg [3:0] bit_count;
    reg [15:0] tick_count;

    initial begin
        cur_state = Wait_st;
        rts = 1'b1;
        bit_count = 4'b0000;
        tick_count = 16'h0000;
    end

    always @(posedge clk) begin

        case(cur_state)
            Wait_st: begin
                tx <= 1'b1;
                if(data_ready == 1'b1) begin
                    cur_state <= Start_st;
                    rts <= 1'b0;
                end
                else rts <= 1'b1;
            end
            Start_st: begin
                tx <= 1'b0;
                tick_count <= tick_count + 1'b1;
                if(tick_count == 5208) begin
                    tick_count <= 0;
                    cur_state <= Data_st;
                end
            end
            Data_st: begin
                tick_count <= tick_count + 1'b1;
                if(tick_count == 5208) begin
                    tick_count <= 0;
                    bit_count <= bit_count + 1'b1;
                end
                else begin 
                    tx <= data[bit_count];
                end
                if(bit_count == 4'b1000) begin
                    cur_state <= Stop_st;
                    tx <= 1'b1;
                    bit_count <= 4'b0000;
                end
            end
            Stop_st: begin
                tx <= 1'b1;
                rts <= 1'b1;
                tick_count <= tick_count + 1'b1;
                if(tick_count == 5208) begin
                    tick_count <= 0;
                    cur_state <= Wait_st;
                end
            end
            default: cur_state <= Wait_st;
        endcase
    end

endmodule

Semester_5/Course_work/Root_calculator/src/src_testbenches/RS232_transmitter_testbench.v
`include "../src_logic/RS232_transmitter.v"

`timescale 1ns/1ps
module RS232_transmitter_testbench;

reg clk;
reg data_ready;
reg [7:0] data;

wire rts;
wire tx;

RS232_transmitter dut (
    .clk(clk),
    .data_ready(data_ready),
    .data(data),
    .rts(rts),
    .tx(tx)
);

always #5 clk = ~clk;

initial begin
    {clk, data, data_ready} = 0;
end

initial begin

    
    $dumpfile("RS232_transmitter_testbench.vcd");
    $dumpvars;

    #200

    data = 8'b01101010;
    data_ready = 1'b1;

    #10

    data_ready = 1'b0;

	#1000000;
	 
    $stop;
    $finish;
end

endmodule

Semester_5/Course_work/Root_calculator/quartus/simulation/modelsim/RS232_transmitter_testbench.vcd
$date
	Sun Nov 13 15:43:22 2022
$end
$version
	Questa Intel Starter FPGA Edition Version 2021.2
$end
$timescale
	1ps
$end

$scope module RS232_transmitter_testbench $end
$var reg 1 ! clk $end
$var reg 1 " data_ready $end
$var reg 8 # data [7:0] $end
$var wire 1 $ rts $end
$var wire 1 % tx $end

$scope module dut $end
$var parameter 32 & CLK_DIVIDER $end
$var parameter 2 ' Wait_st $end
$var parameter 2 ( Start_st $end
$var parameter 2 ) Data_st $end
$var parameter 2 * Stop_st $end
$var wire 1 + clk $end
$var wire 1 , data [7] $end
$var wire 1 - data [6] $end
$var wire 1 . data [5] $end
$var wire 1 / data [4] $end
$var wire 1 0 data [3] $end
$var wire 1 1 data [2] $end
$var wire 1 2 data [1] $end
$var wire 1 3 data [0] $end
$var wire 1 4 data_ready $end
$var reg 1 5 tx $end
$var reg 1 6 rts $end
$var reg 2 7 cur_state [1:0] $end
$var reg 4 8 bit_count [3:0] $end
$var reg 16 9 tick_count [15:0] $end
$upscope $end
$upscope $end
$enddefinitions $end
#0
$dumpvars
0!
0"
b0 #
x5
16
b0 7
b0 8
b0 9
b1010001011000 &
b0 '
b1 (
b10 )
b11 *
1$
x%
04
03
02
01
00
0/
0.
0-
0,
0+
$end
#5000
1!
1+
15
1%
#10000
0!
0+
#15000
1!
1+
#20000
0!
0+
#25000
1!
1+
#30000
0!
0+
#35000
1!
1+
#40000
0!
0+
#45000
1!
1+
#50000
0!
0+
#55000
1!
1+
#60000
0!
0+
#65000
1!
1+
#70000
0!
0+
#75000
1!
1+
#80000
0!
0+
#85000
1!
1+
#90000
0!
0+
#95000
1!
1+
#100000
0!
0+
#105000
1!
1+
#110000
0!
0+
#115000
1!
1+
#120000
0!
0+
#125000
1!
1+
#130000
0!
0+
#135000
1!
1+
#140000
0!
0+
#145000
1!
1+
#150000
0!
0+
#155000
1!
1+
#160000
0!
0+
#165000
1!
1+
#170000
0!
0+
#175000
1!
1+
#180000
0!
0+
#185000
1!
1+
#190000
0!
0+
#195000
1!
1+
#200000
b1101010 #
1"
0!
12
10
1.
1-
14
0+
#205000
1!
1+
b1 7
06
0$
#210000
0"
0!
04
0+
#215000
1!
1+
05
b1 9
0%
#220000
0!
0+
#225000
1!
1+
b10 9
#230000
0!
0+
#235000
1!
1+
b11 9
#240000
0!
0+
#245000
1!
1+
b100 9
#250000
0!
0+
#255000
1!
1+
b101 9
#260000
0!
0+
#265000
1!
1+
b110 9
#270000
0!
0+
#275000
1!
1+
b111 9
#280000
0!
0+
#285000
1!
1+
b1000 9
#290000
0!
0+
#295000
1!
1+
b1001 9
#300000
0!
0+
#305000
1!
1+
b1010 9
#310000
0!
0+
#315000
1!
1+
b1011 9
#320000
0!
0+
#325000
1!
1+
b1100 9
#330000
0!
0+
#335000
1!
1+
b1101 9
#340000
0!
0+
#345000
1!
1+
b1110 9
#350000
0!
0+
#355000
1!
1+
b1111 9
#360000
0!
0+
#365000
1!
1+
b10000 9
#370000
0!
0+
#375000
1!
1+
b10001 9
#380000
0!
0+
#385000
1!
1+
b10010 9
#390000
0!
0+
#395000
1!
1+
b10011 9
#400000
0!
0+
#405000
1!
1+
b10100 9
#410000
0!
0+
#415000
1!
1+
b10101 9
#420000
0!
0+
#425000
1!
1+
b10110 9
#430000
0!
0+
#435000
1!
1+
b10111 9
#440000
0!
0+
#445000
1!
1+
b11000 9
#450000
0!
0+
#455000
1!
1+
b11001 9
#460000
0!
0+
#465000
1!
1+
b11010 9
#470000
0!
0+
#475000
1!
1+
b11011 9
#480000
0!
0+
#485000
1!
1+
b11100 9
#490000
0!
0+
#495000
1!
1+
b11101 9
#500000
0!
0+
#505000
1!
1+
b11110 9
#510000
0!
0+
#515000
1!
1+
b11111 9
#520000
0!
0+
#525000
1!
1+
b100000 9
#530000
0!
0+
#535000
1!
1+
b100001 9
#540000
0!
0+
#545000
1!
1+
b100010 9
#550000
0!
0+
#555000
1!
1+
b100011 9
#560000
0!
0+
#565000
1!
1+
b100100 9
#570000
0!
0+
#575000
1!
1+
b100101 9
#580000
0!
0+
#585000
1!
1+
b100110 9
#590000
0!
0+
#595000
1!
1+
b100111 9
#600000
0!
0+
#605000
1!
1+
b101000 9
#610000
0!
0+
#615000
1!
1+
b101001 9
#620000
0!
0+
#625000
1!
1+
b101010 9
#630000
0!
0+
#635000
1!
1+
b101011 9
#640000
0!
0+
#645000
1!
1+
b101100 9
#650000
0!
0+
#655000
1!
1+
b101101 9
#660000
0!
0+
#665000
1!
1+
b101110 9
#670000
0!
0+
#675000
1!
1+
b101111 9
#680000
0!
0+
#685000
1!
1+
b110000 9
#690000
0!
0+
#695000
1!
1+
b110001 9
#700000
0!
0+
#705000
1!
1+
b110010 9
#710000
0!
0+
#715000
1!
1+
b110011 9
#720000
0!
0+
#725000
1!
1+
b110100 9
#730000
0!
0+
#735000
1!
1+
b110101 9
#740000
0!
0+
#745000
1!
1+
b110110 9
#750000
0!
0+
#755000
1!
1+
b110111 9
#760000
0!
0+
#765000
1!
1+
b111000 9
#770000
0!
0+
#775000
1!
1+
b111001 9
#780000
0!
0+
#785000
1!
1+
b111010 9
#790000
0!
0+
#795000
1!
1+
b111011 9
#800000
0!
0+
#805000
1!
1+
b111100 9
#810000
0!
0+
#815000
1!
1+
b111101 9
#820000
0!
0+
#825000
1!
1+
b111110 9
#830000
0!
0+
#835000
1!
1+
b111111 9
#840000
0!
0+
#845000
1!
1+
b1000000 9
#850000
0!
0+
#855000
1!
1+
b1000001 9
#860000
0!
0+
#865000
1!
1+
b1000010 9
#870000
0!
0+
#875000
1!
1+
b1000011 9
#880000
0!
0+
#885000
1!
1+
b1000100 9
#890000
0!
0+
#895000
1!
1+
b1000101 9
#900000
0!
0+
#905000
1!
1+
b1000110 9
#910000
0!
0+
#915000
1!
1+
b1000111 9
#920000
0!
0+
#925000
1!
1+
b1001000 9
#930000
0!
0+
#935000
1!
1+
b1001001 9
#940000
0!
0+
#945000
1!
1+
b1001010 9
#950000
0!
0+
#955000
1!
1+
b1001011 9
#960000
0!
0+
#965000
1!
1+
b1001100 9
#970000
0!
0+
#975000
1!
1+
b1001101 9
#980000
0!
0+
#985000
1!
1+
b1001110 9
#990000
0!
0+
#995000
1!
1+
b1001111 9
#1000000
0!
0+
#1005000
1!
1+
b1010000 9
#1010000
0!
0+
#1015000
1!
1+
b1010001 9
#1020000
0!
0+
#1025000
1!
1+
b1010010 9
#1030000
0!
0+
#1035000
1!
1+
b1010011 9
#1040000
0!
0+
#1045000
1!
1+
b1010100 9
#1050000
0!
0+
#1055000
1!
1+
b1010101 9
#1060000
0!
0+
#1065000
1!
1+
b1010110 9
#1070000
0!
0+
#1075000
1!
1+
b1010111 9
#1080000
0!
0+
#1085000
1!
1+
b1011000 9
#1090000
0!
0+
#1095000
1!
1+
b1011001 9
#1100000
0!
0+
#1105000
1!
1+
b1011010 9
#1110000
0!
0+
#1115000
1!
1+
b1011011 9
#1120000
0!
0+
#1125000
1!
1+
b1011100 9
#1130000
0!
0+
#1135000
1!
1+
b1011101 9
#1140000
0!
0+
#1145000
1!
1+
b1011110 9
#1150000
0!
0+
#1155000
1!
1+
b1011111 9
#1160000
0!
0+
#1165000
1!
1+
b1100000 9
#1170000
0!
0+
#1175000
1!
1+
b1100001 9
#1180000
0!
0+
#1185000
1!
1+
b1100010 9
#1190000
0!
0+
#1195000
1!
1+
b1100011 9
#1200000
0!
0+
#1205000
1!
1+
b1100100 9
#1210000
0!
0+
#1215000
1!
1+
b1100101 9
#1220000
0!
0+
#1225000
1!
1+
b1100110 9
#1230000
0!
0+
#1235000
1!
1+
b1100111 9
#1240000
0!
0+
#1245000
1!
1+
b1101000 9
#1250000
0!
0+
#1255000
1!
1+
b1101001 9
#1260000
0!
0+
#1265000
1!
1+
b1101010 9
#1270000
0!
0+
#1275000
1!
1+
b1101011 9
#1280000
0!
0+
#1285000
1!
1+
b1101100 9
#1290000
0!
0+
#1295000
1!
1+
b1101101 9
#1300000
0!
0+
#1305000
1!
1+
b1101110 9
#1310000
0!
0+
#1315000
1!
1+
b1101111 9
#1320000
0!
0+
#1325000
1!
1+
b1110000 9
#1330000
0!
0+
#1335000
1!
1+
b1110001 9
#1340000
0!
0+
#1345000
1!
1+
b1110010 9
#1350000
0!
0+
#1355000
1!
1+
b1110011 9
#1360000
0!
0+
#1365000
1!
1+
b1110100 9
#1370000
0!
0+
#1375000
1!
1+
b1110101 9
#1380000
0!
0+
#1385000
1!
1+
b1110110 9
#1390000
0!
0+
#1395000
1!
1+
b1110111 9
#1400000
0!
0+
#1405000
1!
1+
b1111000 9
#1410000
0!
0+
#1415000
1!
1+
b1111001 9
#1420000
0!
0+
#1425000
1!
1+
b1111010 9
#1430000
0!
0+
#1435000
1!
1+
b1111011 9
#1440000
0!
0+
#1445000
1!
1+
b1111100 9
#1450000
0!
0+
#1455000
1!
1+
b1111101 9
#1460000
0!
0+
#1465000
1!
1+
b1111110 9
#1470000
0!
0+
#1475000
1!
1+
b1111111 9
#1480000
0!
0+
#1485000
1!
1+
b10000000 9
#1490000
0!
0+
#1495000
1!
1+
b10000001 9
#1500000
0!
0+
#1505000
1!
1+
b10000010 9
#1510000
0!
0+
#1515000
1!
1+
b10000011 9
#1520000
0!
0+
#1525000
1!
1+
b10000100 9
#1530000
0!
0+
#1535000
1!
1+
b10000101 9
#1540000
0!
0+
#1545000
1!
1+
b10000110 9
#1550000
0!
0+
#1555000
1!
1+
b10000111 9
#1560000
0!
0+
#1565000
1!
1+
b10001000 9
#1570000
0!
0+
#1575000
1!
1+
b10001001 9
#1580000
0!
0+
#1585000
1!
1+
b10001010 9
#1590000
0!
0+
#1595000
1!
1+
b10001011 9
#1600000
0!
0+
#1605000
1!
1+
b10001100 9
#1610000
0!
0+
#1615000
1!
1+
b10001101 9
#1620000
0!
0+
#1625000
1!
1+
b10001110 9
#1630000
0!
0+
#1635000
1!
1+
b10001111 9
#1640000
0!
0+
#1645000
1!
1+
b10010000 9
#1650000
0!
0+
#1655000
1!
1+
b10010001 9
#1660000
0!
0+
#1665000
1!
1+
b10010010 9
#1670000
0!
0+
#1675000
1!
1+
b10010011 9
#1680000
0!
0+
#1685000
1!
1+
b10010100 9
#1690000
0!
0+
#1695000
1!
1+
b10010101 9
#1700000
0!
0+
#1705000
1!
1+
b10010110 9
#1710000
0!
0+
#1715000
1!
1+
b10010111 9
#1720000
0!
0+
#1725000
1!
1+
b10011000 9
#1730000
0!
0+
#1735000
1!
1+
b10011001 9
#1740000
0!
0+
#1745000
1!
1+
b10011010 9
#1750000
0!
0+
#1755000
1!
1+
b10011011 9
#1760000
0!
0+
#1765000
1!
1+
b10011100 9
#1770000
0!
0+
#1775000
1!
1+
b10011101 9
#1780000
0!
0+
#1785000
1!
1+
b10011110 9
#1790000
0!
0+
#1795000
1!
1+
b10011111 9
#1800000
0!
0+
#1805000
1!
1+
b10100000 9
#1810000
0!
0+
#1815000
1!
1+
b10100001 9
#1820000
0!
0+
#1825000
1!
1+
b10100010 9
#1830000
0!
0+
#1835000
1!
1+
b10100011 9
#1840000
0!
0+
#1845000
1!
1+
b10100100 9
#1850000
0!
0+
#1855000
1!
1+
b10100101 9
#1860000
0!
0+
#1865000
1!
1+
b10100110 9
#1870000
0!
0+
#1875000
1!
1+
b10100111 9
#1880000
0!
0+
#1885000
1!
1+
b10101000 9
#1890000
0!
0+
#1895000
1!
1+
b10101001 9
#1900000
0!
0+
#1905000
1!
1+
b10101010 9
#1910000
0!
0+
#1915000
1!
1+
b10101011 9
#1920000
0!
0+
#1925000
1!
1+
b10101100 9
#1930000
0!
0+
#1935000
1!
1+
b10101101 9
#1940000
0!
0+
#1945000
1!
1+
b10101110 9
#1950000
0!
0+
#1955000
1!
1+
b10101111 9
#1960000
0!
0+
#1965000
1!
1+
b10110000 9
#1970000
0!
0+
#1975000
1!
1+
b10110001 9
#1980000
0!
0+
#1985000
1!
1+
b10110010 9
#1990000
0!
0+
#1995000
1!
1+
b10110011 9
#2000000
0!
0+
#2005000
1!
1+
b10110100 9
#2010000
0!
0+
#2015000
1!
1+
b10110101 9
#2020000
0!
0+
#2025000
1!
1+
b10110110 9
#2030000
0!
0+
#2035000
1!
1+
b10110111 9
#2040000
0!
0+
#2045000
1!
1+
b10111000 9
#2050000
0!
0+
#2055000
1!
1+
b10111001 9
#2060000
0!
0+
#2065000
1!
1+
b10111010 9
#2070000
0!
0+
#2075000
1!
1+
b10111011 9
#2080000
0!
0+
#2085000
1!
1+
b10111100 9
#2090000
0!
0+
#2095000
1!
1+
b10111101 9
#2100000
0!
0+
#2105000
1!
1+
b10111110 9
#2110000
0!
0+
#2115000
1!
1+
b10111111 9
#2120000
0!
0+
#2125000
1!
1+
b11000000 9
#2130000
0!
0+
#2135000
1!
1+
b11000001 9
#2140000
0!
0+
#2145000
1!
1+
b11000010 9
#2150000
0!
0+
#2155000
1!
1+
b11000011 9
#2160000
0!
0+
#2165000
1!
1+
b11000100 9
#2170000
0!
0+
#2175000
1!
1+
b11000101 9
#2180000
0!
0+
#2185000
1!
1+
b11000110 9
#2190000
0!
0+
#2195000
1!
1+
b11000111 9
#2200000
0!
0+
#2205000
1!
1+
b11001000 9
#2210000
0!
0+
#2215000
1!
1+
b11001001 9
#2220000
0!
0+
#2225000
1!
1+
b11001010 9
#2230000
0!
0+
#2235000
1!
1+
b11001011 9
#2240000
0!
0+
#2245000
1!
1+
b11001100 9
#2250000
0!
0+
#2255000
1!
1+
b11001101 9
#2260000
0!
0+
#2265000
1!
1+
b11001110 9
#2270000
0!
0+
#2275000
1!
1+
b11001111 9
#2280000
0!
0+
#2285000
1!
1+
b11010000 9
#2290000
0!
0+
#2295000
1!
1+
b11010001 9
#2300000
0!
0+
#2305000
1!
1+
b11010010 9
#2310000
0!
0+
#2315000
1!
1+
b11010011 9
#2320000
0!
0+
#2325000
1!
1+
b11010100 9
#2330000
0!
0+
#2335000
1!
1+
b11010101 9
#2340000
0!
0+
#2345000
1!
1+
b11010110 9
#2350000
0!
0+
#2355000
1!
1+
b11010111 9
#2360000
0!
0+
#2365000
1!
1+
b11011000 9
#2370000
0!
0+
#2375000
1!
1+
b11011001 9
#2380000
0!
0+
#2385000
1!
1+
b11011010 9
#2390000
0!
0+
#2395000
1!
1+
b11011011 9
#2400000
0!
0+
#2405000
1!
1+
b11011100 9
#2410000
0!
0+
#2415000
1!
1+
b11011101 9
#2420000
0!
0+
#2425000
1!
1+
b11011110 9
#2430000
0!
0+
#2435000
1!
1+
b11011111 9
#2440000
0!
0+
#2445000
1!
1+
b11100000 9
#2450000
0!
0+
#2455000
1!
1+
b11100001 9
#2460000
0!
0+
#2465000
1!
1+
b11100010 9
#2470000
0!
0+
#2475000
1!
1+
b11100011 9
#2480000
0!
0+
#2485000
1!
1+
b11100100 9
#2490000
0!
0+
#2495000
1!
1+
b11100101 9
#2500000
0!
0+
#2505000
1!
1+
b11100110 9
#2510000
0!
0+
#2515000
1!
1+
b11100111 9
#2520000
0!
0+
#2525000
1!
1+
b11101000 9
#2530000
0!
0+
#2535000
1!
1+
b11101001 9
#2540000
0!
0+
#2545000
1!
1+
b11101010 9
#2550000
0!
0+
#2555000
1!
1+
b11101011 9
#2560000
0!
0+
#2565000
1!
1+
b11101100 9
#2570000
0!
0+
#2575000
1!
1+
b11101101 9
#2580000
0!
0+
#2585000
1!
1+
b11101110 9
#2590000
0!
0+
#2595000
1!
1+
b11101111 9
#2600000
0!
0+
#2605000
1!
1+
b11110000 9
#2610000
0!
0+
#2615000
1!
1+
b11110001 9
#2620000
0!
0+
#2625000
1!
1+
b11110010 9
#2630000
0!
0+
#2635000
1!
1+
b11110011 9
#2640000
0!
0+
#2645000
1!
1+
b11110100 9
#2650000
0!
0+
#2655000
1!
1+
b11110101 9
#2660000
0!
0+
#2665000
1!
1+
b11110110 9
#2670000
0!
0+
#2675000
1!
1+
b11110111 9
#2680000
0!
0+
#2685000
1!
1+
b11111000 9
#2690000
0!
0+
#2695000
1!
1+
b11111001 9
#2700000
0!
0+
#2705000
1!
1+
b11111010 9
#2710000
0!
0+
#2715000
1!
1+
b11111011 9
#2720000
0!
0+
#2725000
1!
1+
b11111100 9
#2730000
0!
0+
#2735000
1!
1+
b11111101 9
#2740000
0!
0+
#2745000
1!
1+
b11111110 9
#2750000
0!
0+
#2755000
1!
1+
b11111111 9
#2760000
0!
0+
#2765000
1!
1+
b100000000 9
#2770000
0!
0+
#2775000
1!
1+
b100000001 9
#2780000
0!
0+
#2785000
1!
1+
b100000010 9
#2790000
0!
0+
#2795000
1!
1+
b100000011 9
#2800000
0!
0+
#2805000
1!
1+
b100000100 9
#2810000
0!
0+
#2815000
1!
1+
b100000101 9
#2820000
0!
0+
#2825000
1!
1+
b100000110 9
#2830000
0!
0+
#2835000
1!
1+
b100000111 9
#2840000
0!
0+
#2845000
1!
1+
b100001000 9
#2850000
0!
0+
#2855000
1!
1+
b100001001 9
#2860000
0!
0+
#2865000
1!
1+
b100001010 9
#2870000
0!
0+
#2875000
1!
1+
b100001011 9
#2880000
0!
0+
#2885000
1!
1+
b100001100 9
#2890000
0!
0+
#2895000
1!
1+
b100001101 9
#2900000
0!
0+
#2905000
1!
1+
b100001110 9
#2910000
0!
0+
#2915000
1!
1+
b100001111 9
#2920000
0!
0+
#2925000
1!
1+
b100010000 9
#2930000
0!
0+
#2935000
1!
1+
b100010001 9
#2940000
0!
0+
#2945000
1!
1+
b100010010 9
#2950000
0!
0+
#2955000
1!
1+
b100010011 9
#2960000
0!
0+
#2965000
1!
1+
b100010100 9
#2970000
0!
0+
#2975000
1!
1+
b100010101 9
#2980000
0!
0+
#2985000
1!
1+
b100010110 9
#2990000
0!
0+
#2995000
1!
1+
b100010111 9
#3000000
0!
0+
#3005000
1!
1+
b100011000 9
#3010000
0!
0+
#3015000
1!
1+
b100011001 9
#3020000
0!
0+
#3025000
1!
1+
b100011010 9
#3030000
0!
0+
#3035000
1!
1+
b100011011 9
#3040000
0!
0+
#3045000
1!
1+
b100011100 9
#3050000
0!
0+
#3055000
1!
1+
b100011101 9
#3060000
0!
0+
#3065000
1!
1+
b100011110 9
#3070000
0!
0+
#3075000
1!
1+
b100011111 9
#3080000
0!
0+
#3085000
1!
1+
b100100000 9
#3090000
0!
0+
#3095000
1!
1+
b100100001 9
#3100000
0!
0+
#3105000
1!
1+
b100100010 9
#3110000
0!
0+
#3115000
1!
1+
b100100011 9
#3120000
0!
0+
#3125000
1!
1+
b100100100 9
#3130000
0!
0+
#3135000
1!
1+
b100100101 9
#3140000
0!
0+
#3145000
1!
1+
b100100110 9
#3150000
0!
0+
#3155000
1!
1+
b100100111 9
#3160000
0!
0+
#3165000
1!
1+
b100101000 9
#3170000
0!
0+
#3175000
1!
1+
b100101001 9
#3180000
0!
0+
#3185000
1!
1+
b100101010 9
#3190000
0!
0+
#3195000
1!
1+
b100101011 9
#3200000
0!
0+
#3205000
1!
1+
b100101100 9
#3210000
0!
0+
#3215000
1!
1+
b100101101 9
#3220000
0!
0+
#3225000
1!
1+
b100101110 9
#3230000
0!
0+
#3235000
1!
1+
b100101111 9
#3240000
0!
0+
#3245000
1!
1+
b100110000 9
#3250000
0!
0+
#3255000
1!
1+
b100110001 9
#3260000
0!
0+
#3265000
1!
1+
b100110010 9
#3270000
0!
0+
#3275000
1!
1+
b100110011 9
#3280000
0!
0+
#3285000
1!
1+
b100110100 9
#3290000
0!
0+
#3295000
1!
1+
b100110101 9
#3300000
0!
0+
#3305000
1!
1+
b100110110 9
#3310000
0!
0+
#3315000
1!
1+
b100110111 9
#3320000
0!
0+
#3325000
1!
1+
b100111000 9
#3330000
0!
0+
#3335000
1!
1+
b100111001 9
#3340000
0!
0+
#3345000
1!
1+
b100111010 9
#3350000
0!
0+
#3355000
1!
1+
b100111011 9
#3360000
0!
0+
#3365000
1!
1+
b100111100 9
#3370000
0!
0+
#3375000
1!
1+
b100111101 9
#3380000
0!
0+
#3385000
1!
1+
b100111110 9
#3390000
0!
0+
#3395000
1!
1+
b100111111 9
#3400000
0!
0+
#3405000
1!
1+
b101000000 9
#3410000
0!
0+
#3415000
1!
1+
b101000001 9
#3420000
0!
0+
#3425000
1!
1+
b101000010 9
#3430000
0!
0+
#3435000
1!
1+
b101000011 9
#3440000
0!
0+
#3445000
1!
1+
b101000100 9
#3450000
0!
0+
#3455000
1!
1+
b101000101 9
#3460000
0!
0+
#3465000
1!
1+
b101000110 9
#3470000
0!
0+
#3475000
1!
1+
b101000111 9
#3480000
0!
0+
#3485000
1!
1+
b101001000 9
#3490000
0!
0+
#3495000
1!
1+
b101001001 9
#3500000
0!
0+
#3505000
1!
1+
b101001010 9
#3510000
0!
0+
#3515000
1!
1+
b101001011 9
#3520000
0!
0+
#3525000
1!
1+
b101001100 9
#3530000
0!
0+
#3535000
1!
1+
b101001101 9
#3540000
0!
0+
#3545000
1!
1+
b101001110 9
#3550000
0!
0+
#3555000
1!
1+
b101001111 9
#3560000
0!
0+
#3565000
1!
1+
b101010000 9
#3570000
0!
0+
#3575000
1!
1+
b101010001 9
#3580000
0!
0+
#3585000
1!
1+
b101010010 9
#3590000
0!
0+
#3595000
1!
1+
b101010011 9
#3600000
0!
0+
#3605000
1!
1+
b101010100 9
#3610000
0!
0+
#3615000
1!
1+
b101010101 9
#3620000
0!
0+
#3625000
1!
1+
b101010110 9
#3630000
0!
0+
#3635000
1!
1+
b101010111 9
#3640000
0!
0+
#3645000
1!
1+
b101011000 9
#3650000
0!
0+
#3655000
1!
1+
b101011001 9
#3660000
0!
0+
#3665000
1!
1+
b101011010 9
#3670000
0!
0+
#3675000
1!
1+
b101011011 9
#3680000
0!
0+
#3685000
1!
1+
b101011100 9
#3690000
0!
0+
#3695000
1!
1+
b101011101 9
#3700000
0!
0+
#3705000
1!
1+
b101011110 9
#3710000
0!
0+
#3715000
1!
1+
b101011111 9
#3720000
0!
0+
#3725000
1!
1+
b101100000 9
#3730000
0!
0+
#3735000
1!
1+
b101100001 9
#3740000
0!
0+
#3745000
1!
1+
b101100010 9
#3750000
0!
0+
#3755000
1!
1+
b101100011 9
#3760000
0!
0+
#3765000
1!
1+
b101100100 9
#3770000
0!
0+
#3775000
1!
1+
b101100101 9
#3780000
0!
0+
#3785000
1!
1+
b101100110 9
#3790000
0!
0+
#3795000
1!
1+
b101100111 9
#3800000
0!
0+
#3805000
1!
1+
b101101000 9
#3810000
0!
0+
#3815000
1!
1+
b101101001 9
#3820000
0!
0+
#3825000
1!
1+
b101101010 9
#3830000
0!
0+
#3835000
1!
1+
b101101011 9
#3840000
0!
0+
#3845000
1!
1+
b101101100 9
#3850000
0!
0+
#3855000
1!
1+
b101101101 9
#3860000
0!
0+
#3865000
1!
1+
b101101110 9
#3870000
0!
0+
#3875000
1!
1+
b101101111 9
#3880000
0!
0+
#3885000
1!
1+
b101110000 9
#3890000
0!
0+
#3895000
1!
1+
b101110001 9
#3900000
0!
0+
#3905000
1!
1+
b101110010 9
#3910000
0!
0+
#3915000
1!
1+
b101110011 9
#3920000
0!
0+
#3925000
1!
1+
b101110100 9
#3930000
0!
0+
#3935000
1!
1+
b101110101 9
#3940000
0!
0+
#3945000
1!
1+
b101110110 9
#3950000
0!
0+
#3955000
1!
1+
b101110111 9
#3960000
0!
0+
#3965000
1!
1+
b101111000 9
#3970000
0!
0+
#3975000
1!
1+
b101111001 9
#3980000
0!
0+
#3985000
1!
1+
b101111010 9
#3990000
0!
0+
#3995000
1!
1+
b101111011 9
#4000000
0!
0+
#4005000
1!
1+
b101111100 9
#4010000
0!
0+
#4015000
1!
1+
b101111101 9
#4020000
0!
0+
#4025000
1!
1+
b101111110 9
#4030000
0!
0+
#4035000
1!
1+
b101111111 9
#4040000
0!
0+
#4045000
1!
1+
b110000000 9
#4050000
0!
0+
#4055000
1!
1+
b110000001 9
#4060000
0!
0+
#4065000
1!
1+
b110000010 9
#4070000
0!
0+
#4075000
1!
1+
b110000011 9
#4080000
0!
0+
#4085000
1!
1+
b110000100 9
#4090000
0!
0+
#4095000
1!
1+
b110000101 9
#4100000
0!
0+
#4105000
1!
1+
b110000110 9
#4110000
0!
0+
#4115000
1!
1+
b110000111 9
#4120000
0!
0+
#4125000
1!
1+
b110001000 9
#4130000
0!
0+
#4135000
1!
1+
b110001001 9
#4140000
0!
0+
#4145000
1!
1+
b110001010 9
#4150000
0!
0+
#4155000
1!
1+
b110001011 9
#4160000
0!
0+
#4165000
1!
1+
b110001100 9
#4170000
0!
0+
#4175000
1!
1+
b110001101 9
#4180000
0!
0+
#4185000
1!
1+
b110001110 9
#4190000
0!
0+
#4195000
1!
1+
b110001111 9
#4200000
0!
0+
#4205000
1!
1+
b110010000 9
#4210000
0!
0+
#4215000
1!
1+
b110010001 9
#4220000
0!
0+
#4225000
1!
1+
b110010010 9
#4230000
0!
0+
#4235000
1!
1+
b110010011 9
#4240000
0!
0+
#4245000
1!
1+
b110010100 9
#4250000
0!
0+
#4255000
1!
1+
b110010101 9
#4260000
0!
0+
#4265000
1!
1+
b110010110 9
#4270000
0!
0+
#4275000
1!
1+
b110010111 9
#4280000
0!
0+
#4285000
1!
1+
b110011000 9
#4290000
0!
0+
#4295000
1!
1+
b110011001 9
#4300000
0!
0+
#4305000
1!
1+
b110011010 9
#4310000
0!
0+
#4315000
1!
1+
b110011011 9
#4320000
0!
0+
#4325000
1!
1+
b110011100 9
#4330000
0!
0+
#4335000
1!
1+
b110011101 9
#4340000
0!
0+
#4345000
1!
1+
b110011110 9
#4350000
0!
0+
#4355000
1!
1+
b110011111 9
#4360000
0!
0+
#4365000
1!
1+
b110100000 9
#4370000
0!
0+
#4375000
1!
1+
b110100001 9
#4380000
0!
0+
#4385000
1!
1+
b110100010 9
#4390000
0!
0+
#4395000
1!
1+
b110100011 9
#4400000
0!
0+
#4405000
1!
1+
b110100100 9
#4410000
0!
0+
#4415000
1!
1+
b110100101 9
#4420000
0!
0+
#4425000
1!
1+
b110100110 9
#4430000
0!
0+
#4435000
1!
1+
b110100111 9
#4440000
0!
0+
#4445000
1!
1+
b110101000 9
#4450000
0!
0+
#4455000
1!
1+
b110101001 9
#4460000
0!
0+
#4465000
1!
1+
b110101010 9
#4470000
0!
0+
#4475000
1!
1+
b110101011 9
#4480000
0!
0+
#4485000
1!
1+
b110101100 9
#4490000
0!
0+
#4495000
1!
1+
b110101101 9
#4500000
0!
0+
#4505000
1!
1+
b110101110 9
#4510000
0!
0+
#4515000
1!
1+
b110101111 9
#4520000
0!
0+
#4525000
1!
1+
b110110000 9
#4530000
0!
0+
#4535000
1!
1+
b110110001 9
#4540000
0!
0+
#4545000
1!
1+
b110110010 9
#4550000
0!
0+
#4555000
1!
1+
b110110011 9
#4560000
0!
0+
#4565000
1!
1+
b110110100 9
#4570000
0!
0+
#4575000
1!
1+
b110110101 9
#4580000
0!
0+
#4585000
1!
1+
b110110110 9
#4590000
0!
0+
#4595000
1!
1+
b110110111 9
#4600000
0!
0+
#4605000
1!
1+
b110111000 9
#4610000
0!
0+
#4615000
1!
1+
b110111001 9
#4620000
0!
0+
#4625000
1!
1+
b110111010 9
#4630000
0!
0+
#4635000
1!
1+
b110111011 9
#4640000
0!
0+
#4645000
1!
1+
b110111100 9
#4650000
0!
0+
#4655000
1!
1+
b110111101 9
#4660000
0!
0+
#4665000
1!
1+
b110111110 9
#4670000
0!
0+
#4675000
1!
1+
b110111111 9
