Semester_5/Course_work/Root_calculator/src/src_logic/RS232_reciever.v
module RS232_reciever #(
//   parameter CLK_DIVIDER = 5208 // 9600 baud 50MHz
//	  parameter CLK_DIVIDER = 1042 // 9600 baud 10MHZ
	  parameter CLK_DIVIDER = 3125 // 9600 baud 30MHZ
)(
    input clk,
    input rx,
    output reg [7:0] data,
    output reg error,
    output reg data_ready
);

    localparam Wait_st = 2'b00;
    localparam Start_st = 2'b01;
    localparam Data_st = 2'b10;
    localparam Stop_st = 2'b11;

    reg [1:0] cur_state, next_state;
    reg [3:0] bit_count;
    reg [15:0] tick_count;

    initial begin
        cur_state = Wait_st;
        next_state = Wait_st;
        error = 1'b0;
        data_ready = 1'b0;
        bit_count = 4'b0000;
        tick_count = 16'h0000;
    end

    always @(posedge clk) begin
        cur_state <= next_state;

        case(cur_state)
            Wait_st: begin
                data <= 0;
                error <= 1'b0;
                tick_count <= 16'h0000;
                bit_count <= 4'b0000;
                if(rx == 1'b0) begin
                    next_state <= Start_st;
                end
            end
            Start_st: begin
                tick_count <= tick_count + 1'b1;
                if(tick_count == CLK_DIVIDER/2) begin
                    if(rx == 1'b1) begin
                        error <= 1'b1;
                        next_state <= Wait_st;
                    end 
                    else begin
                        error <= 1'b0;
                    end
                end
                if(tick_count == CLK_DIVIDER) begin
                    tick_count <= 16'h0000;
                    next_state <= Data_st;
                end
            end
            Data_st: begin
                tick_count <= tick_count + 1'b1;
                if(tick_count == CLK_DIVIDER/2) begin
                    data[bit_count] <= rx;
                    bit_count <= bit_count + 1'b1;
                end 
                else begin
                    if(tick_count == CLK_DIVIDER) begin
                        tick_count <= 0;
                        if (bit_count == 4'b1000) begin
                            bit_count <= 4'b0000;
                            next_state <= Stop_st;
                        end
                        else begin
                            next_state <= Data_st;
                        end
                    end
                end
            end
            Stop_st: begin
                tick_count <= tick_count + 1'b1;
                if(tick_count == CLK_DIVIDER/2) begin
                    if(rx == 1'b1) begin
                        data_ready <= 1'b1;
                        error <= 1'b0;
                    end 
                    else begin
                        error <= 1'b1;
                        data_ready <= 0;
                        next_state <= Wait_st;
                    end
                end
                else begin
                    if(tick_count == CLK_DIVIDER) begin
                        tick_count <= 16'h0000;
                        data_ready <= 1'b0;
                        next_state <= Wait_st;
                    end
                end
            end
            default: next_state <= Wait_st;
        endcase
    end

endmodule

Semester_5/Course_work/Root_calculator/src/src_testbenches/RS232_reciever_testbench.v
`include "../src_logic/RS232_reciever.v"

`timescale 1ns/1ps

module RS232_reciever_testbench;

    reg clk;
    reg rx;

    wire data_ready;
    wire error;
    wire [7:0] data;

    reg [7:0] in_data;

    integer i;

    RS232_reciever dut (
        .clk(clk),
        .rx(rx),
        .error(error),
        .data_ready(data_ready),
        .data(data)
    );

    always #5 clk = ~clk;

    initial begin
        clk = 0;
        rx = 1;
        in_data = 8'b01101010;
        i = 0;
    end

    initial begin

        $dumpfile("RS232_reciever_testbench.vcd");
        $dumpvars;

        #200;

        rx = 0; // start bit

        #52080;  // data byte 01101010

        for(i = 0; i < 8; i = i + 1) begin
            rx = in_data[i];
            #52080;
        end 

        rx = 1; // stop bit

        #52080

        $stop;
        $finish;
    end

endmodule

Semester_5/Course_work/Root_calculator/quartus/simulation/modelsim/RS232_reciever_testbench.vcd
$date
	Mon Nov 14 13:17:04 2022
$end
$version
	Questa Intel Starter FPGA Edition Version 2021.2
$end
$timescale
	1ps
$end

$scope module RS232_reciever_testbench $end
$var reg 1 ! clk $end
$var reg 1 " rx $end
$var wire 1 # data_ready $end
$var wire 1 $ error $end
$var wire 1 % data [7] $end
$var wire 1 & data [6] $end
$var wire 1 ' data [5] $end
$var wire 1 ( data [4] $end
$var wire 1 ) data [3] $end
$var wire 1 * data [2] $end
$var wire 1 + data [1] $end
$var wire 1 , data [0] $end
$var reg 8 - in_data [7:0] $end
$var integer 32 . i $end

$scope module dut $end
$var parameter 32 / CLK_DIVIDER $end
$var parameter 2 0 Wait_st $end
$var parameter 2 1 Start_st $end
$var parameter 2 2 Data_st $end
$var parameter 2 3 Stop_st $end
$var wire 1 4 clk $end
$var wire 1 5 rx $end
$var reg 8 6 data [7:0] $end
$var reg 1 7 error $end
$var reg 1 8 data_ready $end
$var reg 2 9 cur_state [1:0] $end
$var reg 2 : next_state [1:0] $end
$var reg 4 ; bit_count [3:0] $end
$var reg 16 < tick_count [15:0] $end
$upscope $end
$upscope $end
$enddefinitions $end
#0
$dumpvars
0!
1"
b1101010 -
bx 6
07
08
b0 9
b0 :
b0 ;
b0 <
b1010001011000 /
b0 0
b1 1
b10 2
b11 3
b0 .
0#
0$
x,
x+
x*
x)
x(
x'
x&
x%
15
04
$end
#5000
1!
14
b0 6
0,
0+
0*
0)
0(
0'
0&
0%
#10000
0!
04
#15000
1!
14
#20000
0!
04
#25000
1!
14
#30000
0!
04
#35000
1!
14
#40000
0!
04
#45000
1!
14
#50000
0!
04
#55000
1!
14
#60000
0!
04
#65000
1!
14
#70000
0!
04
#75000
1!
14
#80000
0!
04
#85000
1!
14
#90000
0!
04
#95000
1!
14
#100000
0!
04
#105000
1!
14
#110000
0!
04
#115000
1!
14
#120000
0!
04
#125000
1!
14
#130000
0!
04
#135000
1!
14
#140000
0!
04
#145000
1!
14
#150000
0!
04
#155000
1!
14
#160000
0!
04
#165000
1!
14
#170000
0!
04
#175000
1!
14
#180000
0!
04
#185000
1!
14
#190000
0!
04
#195000
1!
14
#200000
0"
0!
05
04
#205000
1!
14
b1 :
#210000
0!
04
#215000
1!
14
b1 9
#220000
0!
04
#225000
1!
14
b1 <
#230000
0!
04
#235000
1!
14
b10 <
#240000
0!
04
#245000
1!
14
b11 <
#250000
0!
04
#255000
1!
14
b100 <
#260000
0!
04
#265000
1!
14
b101 <
#270000
0!
04
#275000
1!
14
b110 <
#280000
0!
04
#285000
1!
14
b111 <
#290000
0!
04
#295000
1!
14
b1000 <
#300000
0!
04
#305000
1!
14
b1001 <
#310000
0!
04
#315000
1!
14
b1010 <
#320000
0!
04
#325000
1!
14
b1011 <
#330000
0!
04
#335000
1!
14
b1100 <
#340000
0!
04
#345000
1!
14
b1101 <
#350000
0!
04
#355000
1!
14
b1110 <
#360000
0!
04
#365000
1!
14
b1111 <
#370000
0!
04
#375000
1!
14
b10000 <
#380000
0!
04
#385000
1!
14
b10001 <
#390000
0!
04
#395000
1!
14
b10010 <
#400000
0!
04
#405000
1!
14
b10011 <
#410000
0!
04
#415000
1!
14
b10100 <
#420000
0!
04
#425000
1!
14
b10101 <
#430000
0!
04
#435000
1!
14
b10110 <
#440000
0!
04
#445000
1!
14
b10111 <
#450000
0!
04
#455000
1!
14
b11000 <
#460000
0!
04
#465000
1!
14
b11001 <
#470000
0!
04
#475000
1!
14
b11010 <
#480000
0!
04
#485000
1!
14
b11011 <
#490000
0!
04
#495000
1!
14
b11100 <
#500000
0!
04
#505000
1!
14
b11101 <
#510000
0!
04
#515000
1!
14
b11110 <
#520000
0!
04
#525000
1!
14
b11111 <
#530000
0!
04
#535000
1!
14
b100000 <
#540000
0!
04
#545000
1!
14
b100001 <
#550000
0!
04
#555000
1!
14
b100010 <
#560000
0!
04
#565000
1!
14
b100011 <
#570000
0!
04
#575000
1!
14
b100100 <
#580000
0!
04
#585000
1!
14
b100101 <
#590000
0!
04
#595000
1!
14
b100110 <
#600000
0!
04
#605000
1!
14
b100111 <
#610000
0!
04
#615000
1!
14
b101000 <
#620000
0!
04
#625000
1!
14
b101001 <
#630000
0!
04
#635000
1!
14
b101010 <
#640000
0!
04
#645000
1!
14
b101011 <
#650000
0!
04
#655000
1!
14
b101100 <
#660000
0!
04
#665000
1!
14
b101101 <
#670000
0!
04
#675000
1!
14
b101110 <
#680000
0!
04
#685000
1!
14
b101111 <
#690000
0!
04
#695000
1!
14
b110000 <
#700000
0!
04
#705000
1!
14
b110001 <
#710000
0!
04
#715000
1!
14
b110010 <
#720000
0!
04
#725000
1!
14
b110011 <
#730000
0!
04
#735000
1!
14
b110100 <
#740000
0!
04
#745000
1!
14
b110101 <
#750000
0!
04
#755000
1!
14
b110110 <
#760000
0!
04
#765000
1!
14
b110111 <
#770000
0!
04
#775000
1!
14
b111000 <
#780000
0!
04
#785000
1!
14
b111001 <
#790000
0!
04
#795000
1!
14
b111010 <
#800000
0!
04
#805000
1!
14
b111011 <
#810000
0!
04
#815000
1!
14
b111100 <
#820000
0!
04
#825000
1!
14
b111101 <
#830000
0!
04
#835000
1!
14
b111110 <
#840000
0!
04
#845000
1!
14
b111111 <
#850000
0!
04
#855000
1!
14
b1000000 <
#860000
0!
04
#865000
1!
14
b1000001 <
#870000
0!
04
#875000
1!
14
b1000010 <
#880000
0!
04
#885000
1!
14
b1000011 <
#890000
0!
04
#895000
1!
14
b1000100 <
#900000
0!
04
#905000
1!
14
b1000101 <
#910000
0!
04
#915000
1!
14
b1000110 <
#920000
0!
04
#925000
1!
14
b1000111 <
#930000
0!
04
#935000
1!
14
b1001000 <
#940000
0!
04
#945000
1!
14
b1001001 <
#950000
0!
04
#955000
1!
14
b1001010 <
#960000
0!
04
#965000
1!
14
b1001011 <
#970000
0!
04
#975000
1!
14
b1001100 <
#980000
0!
04
#985000
1!
14
b1001101 <
#990000
0!
04
#995000
1!
14
b1001110 <
#1000000
0!
04
#1005000
1!
14
b1001111 <
#1010000
0!
04
#1015000
1!
14
b1010000 <
#1020000
0!
04
#1025000
1!
14
b1010001 <
#1030000
0!
04
#1035000
1!
14
b1010010 <
#1040000
0!
04
#1045000
1!
14
b1010011 <
#1050000
0!
04
#1055000
1!
14
b1010100 <
#1060000
0!
04
#1065000
1!
14
b1010101 <
#1070000
0!
04
#1075000
1!
14
b1010110 <
#1080000
0!
04
#1085000
1!
14
b1010111 <
#1090000
0!
04
#1095000
1!
14
b1011000 <
#1100000
0!
04
#1105000
1!
14
b1011001 <
#1110000
0!
04
#1115000
1!
14
b1011010 <
#1120000
0!
04
#1125000
1!
14
b1011011 <
#1130000
0!
04
#1135000
1!
14
b1011100 <
#1140000
0!
04
#1145000
1!
14
b1011101 <
#1150000
0!
04
#1155000
1!
14
b1011110 <
#1160000
0!
04
#1165000
1!
14
b1011111 <
#1170000
0!
04
#1175000
1!
14
b1100000 <
#1180000
0!
04
#1185000
1!
14
b1100001 <
#1190000
0!
04
#1195000
1!
14
b1100010 <
#1200000
0!
04
#1205000
1!
14
b1100011 <
#1210000
0!
04
#1215000
1!
14
b1100100 <
#1220000
0!
04
#1225000
1!
14
b1100101 <
#1230000
0!
04
#1235000
1!
14
b1100110 <
#1240000
0!
04
#1245000
1!
14
b1100111 <
#1250000
0!
04
#1255000
1!
14
b1101000 <
#1260000
0!
04
#1265000
1!
14
b1101001 <
#1270000
0!
04
#1275000
1!
14
b1101010 <
#1280000
0!
04
#1285000
1!
14
b1101011 <
#1290000
0!
04
#1295000
1!
14
b1101100 <
#1300000
0!
04
#1305000
1!
14
b1101101 <
#1310000
0!
04
#1315000
1!
14
b1101110 <
#1320000
0!
04
#1325000
1!
14
b1101111 <
#1330000
0!
04
#1335000
1!
14
b1110000 <
#1340000
0!
04
#1345000
1!
14
b1110001 <
#1350000
0!
04
#1355000
1!
14
b1110010 <
#1360000
0!
04
#1365000
1!
14
b1110011 <
#1370000
0!
04
#1375000
1!
14
b1110100 <
#1380000
0!
04
#1385000
1!
14
b1110101 <
#1390000
0!
04
#1395000
1!
14
b1110110 <
#1400000
0!
04
#1405000
1!
14
b1110111 <
#1410000
0!
04
#1415000
1!
14
b1111000 <
#1420000
0!
04
#1425000
1!
14
b1111001 <
#1430000
0!
04
#1435000
1!
14
b1111010 <
#1440000
0!
04
#1445000
1!
14
b1111011 <
#1450000
0!
04
#1455000
1!
14
b1111100 <
#1460000
0!
04
#1465000
1!
14
b1111101 <
#1470000
0!
04
#1475000
1!
14
b1111110 <
#1480000
0!
04
#1485000
1!
14
b1111111 <
#1490000
0!
04
#1495000
1!
14
b10000000 <
#1500000
0!
04
#1505000
1!
14
b10000001 <
#1510000
0!
04
#1515000
1!
14
b10000010 <
#1520000
0!
04
#1525000
1!
14
b10000011 <
#1530000
0!
04
#1535000
1!
14
b10000100 <
#1540000
0!
04
#1545000
1!
14
b10000101 <
#1550000
0!
04
#1555000
1!
14
b10000110 <
#1560000
0!
04
#1565000
1!
14
b10000111 <
#1570000
0!
04
#1575000
1!
14
b10001000 <
#1580000
0!
04
#1585000
1!
14
b10001001 <
#1590000
0!
04
#1595000
1!
14
b10001010 <
#1600000
0!
04
#1605000
1!
14
b10001011 <
#1610000
0!
04
#1615000
1!
14
b10001100 <
#1620000
0!
04
#1625000
1!
14
b10001101 <
#1630000
0!
04
#1635000
1!
14
b10001110 <
#1640000
0!
04
#1645000
1!
14
b10001111 <
#1650000
0!
04
#1655000
1!
14
b10010000 <
#1660000
0!
04
#1665000
1!
14
b10010001 <
#1670000
0!
04
#1675000
1!
14
b10010010 <
#1680000
0!
04
#1685000
1!
14
b10010011 <
#1690000
0!
04
#1695000
1!
14
b10010100 <
#1700000
0!
04
#1705000
1!
14
b10010101 <
#1710000
0!
04
#1715000
1!
14
b10010110 <
#1720000
0!
04
#1725000
1!
14
b10010111 <
#1730000
0!
04
#1735000
1!
14
b10011000 <
#1740000
0!
04
#1745000
1!
14
b10011001 <
#1750000
0!
04
#1755000
1!
14
b10011010 <
#1760000
0!
04
#1765000
1!
14
b10011011 <
#1770000
0!
04
#1775000
1!
14
b10011100 <
#1780000
0!
04
#1785000
1!
14
b10011101 <
#1790000
0!
04
#1795000
1!
14
b10011110 <
#1800000
0!
04
#1805000
1!
14
b10011111 <
#1810000
0!
04
#1815000
1!
14
b10100000 <
#1820000
0!
04
#1825000
1!
14
b10100001 <
#1830000
0!
04
#1835000
1!
14
b10100010 <
#1840000
0!
04
#1845000
1!
14
b10100011 <
#1850000
0!
04
#1855000
1!
14
b10100100 <
#1860000
0!
04
#1865000
1!
14
b10100101 <
#1870000
0!
04
#1875000
1!
14
b10100110 <
#1880000
0!
04
#1885000
1!
14
b10100111 <
#1890000
0!
04
#1895000
1!
14
b10101000 <
#1900000
0!
04
#1905000
1!
14
b10101001 <
#1910000
0!
04
#1915000
1!
14
b10101010 <
#1920000
0!
04
#1925000
1!
14
b10101011 <
#1930000
0!
04
#1935000
1!
14
b10101100 <
#1940000
0!
04
#1945000
1!
14
b10101101 <
#1950000
0!
04
#1955000
1!
14
b10101110 <
#1960000
0!
04
#1965000
1!
14
b10101111 <
#1970000
0!
04
#1975000
1!
14
b10110000 <
#1980000
0!
04
#1985000
1!
14
b10110001 <
#1990000
0!
04
#1995000
1!
14
b10110010 <
#2000000
0!
04
#2005000
1!
14
b10110011 <
#2010000
0!
04
#2015000
1!
14
b10110100 <
#2020000
0!
04
#2025000
1!
14
b10110101 <
#2030000
0!
04
#2035000
1!
14
b10110110 <
#2040000
0!
04
#2045000
1!
14
b10110111 <
#2050000
0!
04
#2055000
1!
14
b10111000 <
#2060000
0!
04
#2065000
1!
14
b10111001 <
#2070000
0!
04
#2075000
1!
14
b10111010 <
#2080000
0!
04
#2085000
1!
14
b10111011 <
#2090000
0!
04
#2095000
1!
14
b10111100 <
#2100000
0!
04
#2105000
1!
14
b10111101 <
#2110000
0!
04
#2115000
1!
14
b10111110 <
#2120000
0!
04
#2125000
1!
14
b10111111 <
#2130000
0!
04
#2135000
1!
14
b11000000 <
#2140000
0!
04
#2145000
1!
14
b11000001 <
#2150000
0!
04
#2155000
1!
14
b11000010 <
#2160000
0!
04
#2165000
1!
14
b11000011 <
#2170000
0!
04
#2175000
1!
14
b11000100 <
#2180000
0!
04
#2185000
1!
14
b11000101 <
#2190000
0!
04
#2195000
1!
14
b11000110 <
#2200000
0!
04
#2205000
1!
14
b11000111 <
#2210000
0!
04
#2215000
1!
14
b11001000 <
#2220000
0!
04
#2225000
1!
14
b11001001 <
#2230000
0!
04
#2235000
1!
14
b11001010 <
#2240000
0!
04
#2245000
1!
14
b11001011 <
#2250000
0!
04
#2255000
1!
14
b11001100 <
#2260000
0!
04
#2265000
1!
14
b11001101 <
#2270000
0!
04
#2275000
1!
14
b11001110 <
#2280000
0!
04
#2285000
1!
14
b11001111 <
#2290000
0!
04
#2295000
1!
14
b11010000 <
#2300000
0!
04
#2305000
1!
14
b11010001 <
#2310000
0!
04
#2315000
1!
14
b11010010 <
#2320000
0!
04
#2325000
1!
14
b11010011 <
#2330000
0!
04
#2335000
1!
14
b11010100 <
#2340000
0!
04
#2345000
1!
14
b11010101 <
#2350000
0!
04
#2355000
1!
14
b11010110 <
#2360000
0!
04
#2365000
1!
14
b11010111 <
#2370000
0!
04
#2375000
1!
14
b11011000 <
#2380000
0!
04
#2385000
1!
14
b11011001 <
#2390000
0!
04
#2395000
1!
14
b11011010 <
#2400000
0!
04
#2405000
1!
14
b11011011 <
#2410000
0!
04
#2415000
1!
14
b11011100 <
#2420000
0!
04
#2425000
1!
14
b11011101 <
#2430000
0!
04
#2435000
1!
14
b11011110 <
#2440000
0!
04
#2445000
1!
14
b11011111 <
#2450000
0!
04
#2455000
1!
14
b11100000 <
#2460000
0!
04
#2465000
1!
14
b11100001 <
#2470000
0!
04
#2475000
1!
14
b11100010 <
#2480000
0!
04
#2485000
1!
14
b11100011 <
#2490000
0!
04
#2495000
1!
14
b11100100 <
#2500000
0!
04
#2505000
1!
14
b11100101 <
#2510000
0!
04
#2515000
1!
14
b11100110 <
#2520000
0!
04
#2525000
1!
14
b11100111 <
#2530000
0!
04
#2535000
1!
14
b11101000 <
#2540000
0!
04
#2545000
1!
14
b11101001 <
#2550000
0!
04
#2555000
1!
14
b11101010 <
#2560000
0!
04
#2565000
1!
14
b11101011 <
#2570000
0!
04
#2575000
1!
14
b11101100 <
#2580000
0!
04
#2585000
1!
14
b11101101 <
#2590000
0!
04
#2595000
1!
14
b11101110 <
#2600000
0!
04
#2605000
1!
14
b11101111 <
#2610000
0!
04
#2615000
1!
14
b11110000 <
#2620000
0!
04
#2625000
1!
14
b11110001 <
#2630000
0!
04
#2635000
1!
14
b11110010 <
#2640000
0!
04
#2645000
1!
14
b11110011 <
#2650000
0!
04
#2655000
1!
14
b11110100 <
#2660000
0!
04
#2665000
1!
14
b11110101 <
#2670000
0!
04
#2675000
1!
14
b11110110 <
#2680000
0!
04
#2685000
1!
14
b11110111 <
#2690000
0!
04
#2695000
1!
14
b11111000 <
#2700000
0!
04
#2705000
1!
14
b11111001 <
#2710000
0!
04
#2715000
1!
14
b11111010 <
#2720000
0!
04
#2725000
1!
14
b11111011 <
#2730000
0!
04
#2735000
1!
14
b11111100 <
#2740000
0!
04
#2745000
1!
14
b11111101 <
#2750000
0!
04
#2755000
1!
14
b11111110 <
#2760000
0!
04
#2765000
1!
14
b11111111 <
#2770000
0!
04
#2775000
1!
14
b100000000 <
#2780000
0!
04
#2785000
1!
14
b100000001 <
#2790000
0!
04
#2795000
1!
14
b100000010 <
#2800000
0!
04
#2805000
1!
14
b100000011 <
#2810000
0!
04
#2815000
1!
14
b100000100 <
#2820000
0!
04
#2825000
1!
14
b100000101 <
#2830000
0!
04
#2835000
1!
14
b100000110 <
#2840000
0!
04
#2845000
1!
14
b100000111 <
#2850000
0!
04
#2855000
1!
14
b100001000 <
#2860000
0!
04
#2865000
1!
14
b100001001 <
#2870000
0!
04
#2875000
1!
14
b100001010 <
#2880000
0!
04
#2885000
1!
14
b100001011 <
#2890000
0!
04
#2895000
1!
14
b100001100 <
#2900000
0!
04
#2905000
1!
14
b100001101 <
#2910000
0!
04
#2915000
1!
14
b100001110 <
#2920000
0!
04
#2925000
1!
14
b100001111 <
#2930000
0!
04
#2935000
1!
14
b100010000 <
#2940000
0!
04
#2945000
1!
14
b100010001 <
#2950000
0!
04
#2955000
1!
14
b100010010 <
#2960000
0!
04
#2965000
1!
14
b100010011 <
#2970000
0!
04
#2975000
1!
14
b100010100 <
#2980000
0!
04
#2985000
1!
14
b100010101 <
#2990000
0!
04
#2995000
1!
14
b100010110 <
#3000000
0!
04
#3005000
1!
14
b100010111 <
#3010000
0!
04
#3015000
1!
14
b100011000 <
#3020000
0!
04
#3025000
1!
14
b100011001 <
#3030000
0!
04
#3035000
1!
14
b100011010 <
#3040000
0!
04
#3045000
1!
14
b100011011 <
#3050000
0!
04
#3055000
1!
14
b100011100 <
#3060000
0!
04
#3065000
1!
14
b100011101 <
#3070000
0!
04
#3075000
1!
14
b100011110 <
#3080000
0!
04
#3085000
1!
14
b100011111 <
#3090000
0!
04
#3095000
1!
14
b100100000 <
#3100000
0!
04
#3105000
1!
14
b100100001 <
#3110000
0!
04
#3115000
1!
14
b100100010 <
#3120000
0!
04
#3125000
1!
14
b100100011 <
#3130000
0!
04
#3135000
1!
14
b100100100 <
#3140000
0!
04
#3145000
1!
14
b100100101 <
#3150000
0!
04
#3155000
1!
14
b100100110 <
#3160000
0!
04
#3165000
1!
14
b100100111 <
#3170000
0!
04
#3175000
1!
14
b100101000 <
#3180000
0!
04
#3185000
1!
14
b100101001 <
#3190000
0!
04
#3195000
1!
14
b100101010 <
#3200000
0!
04
#3205000
1!
14
b100101011 <
#3210000
0!
04
#3215000
1!
14
b100101100 <
#3220000
0!
04
#3225000
1!
14
b100101101 <
#3230000
0!
04
#3235000
1!
14
b100101110 <
#3240000
0!
04
#3245000
1!
14
b100101111 <
#3250000
0!
04
#3255000
1!
14
b100110000 <
#3260000
0!
04
#3265000
1!
14
b100110001 <
#3270000
0!
04
#3275000
1!
14
b100110010 <
#3280000
0!
04
#3285000
1!
14
b100110011 <
#3290000
0!
04
#3295000
1!
14
b100110100 <
#3300000
0!
04
#3305000
1!
14
b100110101 <
#3310000
0!
04
#3315000
1!
14
b100110110 <
#3320000
0!
04
#3325000
1!
14
b100110111 <
#3330000
0!
04
#3335000
1!
14
b100111000 <
#3340000
0!
04
#3345000
1!
14
b100111001 <
#3350000
0!
04
#3355000
1!
14
b100111010 <
#3360000
0!
04
#3365000
1!
14
b100111011 <
#3370000
0!
04
#3375000
1!
14
b100111100 <
#3380000
0!
04
#3385000
1!
14
b100111101 <
#3390000
0!
04
#3395000
1!
14
b100111110 <
#3400000
0!
04
#3405000
1!
14
b100111111 <
#3410000
0!
04
#3415000
1!
14
b101000000 <
#3420000
0!
04
#3425000
1!
14
b101000001 <
#3430000
0!
04
#3435000
1!
14
b101000010 <
#3440000
0!
04
#3445000
1!
14
b101000011 <
#3450000
0!
04
#3455000
1!
14
b101000100 <
#3460000
0!
04
#3465000
1!
14
b101000101 <
#3470000
0!
04
#3475000
1!
14
b101000110 <
#3480000
0!
04
#3485000
1!
14
b101000111 <
#3490000
0!
04
#3495000
1!
14
b101001000 <
#3500000
0!
04
#3505000
1!
14
b101001001 <
#3510000
0!
04
#3515000
1!
14
b101001010 <
#3520000
0!
04
#3525000
1!
14
b101001011 <
#3530000
0!
04
#3535000
1!
14
b101001100 <
#3540000
0!
04
#3545000
1!
14
b101001101 <
#3550000
0!
04
#3555000
1!
14
b101001110 <
#3560000
0!
04
#3565000
1!
14
b101001111 <
#3570000
0!
04
#3575000
1!
14
b101010000 <
#3580000
0!
04
#3585000
1!
14
b101010001 <
#3590000
0!
04
#3595000
1!
14
b101010010 <
#3600000
0!
04
#3605000
1!
14
b101010011 <
#3610000
0!
04
#3615000
1!
14
b101010100 <
#3620000
0!
04
#3625000
1!
14
b101010101 <
#3630000
0!
04
#3635000
1!
14
b101010110 <
#3640000
0!
04
#3645000
1!
14
b101010111 <
#3650000
0!
04
#3655000
1!
14
b101011000 <
#3660000
0!
04
#3665000
1!
14
b101011001 <
#3670000
0!
04
#3675000
1!
14
b101011010 <
#3680000
0!
04
#3685000
1!
14
b101011011 <
#3690000
0!
04
#3695000
1!
14
b101011100 <
#3700000
0!
04
#3705000
1!
14
b101011101 <
#3710000
0!
04
#3715000
1!
14
b101011110 <
#3720000
0!
04
#3725000
1!
14
b101011111 <
#3730000
0!
04
#3735000
1!
14
b101100000 <
#3740000
0!
04
#3745000
1!
14
b101100001 <
#3750000
0!
04
#3755000
1!
14
b101100010 <
#3760000
0!
04
#3765000
1!
14
b101100011 <
#3770000
0!
04
#3775000
1!
14
b101100100 <
#3780000
0!
04
#3785000
1!
14
b101100101 <
#3790000
0!
04
#3795000
1!
14
b101100110 <
#3800000
0!
04
#3805000
1!
14
b101100111 <
#3810000
0!
04
#3815000
1!
14
b101101000 <
#3820000
0!
04
#3825000
1!
14
b101101001 <
#3830000
0!
04
#3835000
1!
14
b101101010 <
#3840000
0!
04
#3845000
1!
14
b101101011 <
#3850000
0!
04
#3855000
1!
14
b101101100 <
#3860000
0!
04
#3865000
1!
14
b101101101 <
#3870000
0!
04
#3875000
1!
14
b101101110 <
#3880000
0!
04
#3885000
1!
14
b101101111 <
#3890000
0!
04
#3895000
1!
14
b101110000 <
#3900000
0!
04
#3905000
1!
14
b101110001 <
#3910000
0!
04
#3915000
1!
14
b101110010 <
#3920000
0!
04
#3925000
1!
14
b101110011 <
#3930000
0!
04
#3935000
1!
14
b101110100 <
#3940000
0!
04
#3945000
1!
14
b101110101 <
#3950000
0!
04
#3955000
1!
14
b101110110 <
#3960000
0!
04
#3965000
1!
14
b101110111 <
#3970000
0!
04
#3975000
1!
14
b101111000 <
#3980000
0!
04
#3985000
1!
14
b101111001 <
#3990000
0!
04
#3995000
1!
14
b101111010 <
#4000000
0!
04
#4005000
1!
14
b101111011 <
#4010000
0!
04
#4015000
1!
14
b101111100 <
#4020000
0!
04
#4025000
1!
14
b101111101 <
#4030000
0!
04
#4035000
1!
14
b101111110 <
#4040000
0!
04
#4045000
1!
14
b101111111 <
#4050000
0!
04
#4055000
1!
14
b110000000 <
#4060000
0!
04
#4065000
1!
14
b110000001 <
#4070000
0!
04
#4075000
1!
14
b110000010 <
#4080000
0!
04
#4085000
1!
14
b110000011 <
#4090000
0!
04
#4095000
1!
14
b110000100 <
#4100000
0!
04
#4105000
1!
14
b110000101 <
#4110000
0!
04
#4115000
1!
14
b110000110 <
#4120000
0!
04
#4125000
1!
14
b110000111 <
#4130000
0!
04
#4135000
1!
14
b110001000 <
#4140000
0!
04
#4145000
1!
14
b110001001 <
#4150000
0!
04
#4155000
1!
14
b110001010 <
#4160000
0!
04
#4165000
1!
14
b110001011 <
#4170000
0!
04
#4175000
1!
14
b110001100 <
#4180000
0!
04
#4185000
1!
14
b110001101 <
#4190000
0!
04
#4195000
1!
14
b110001110 <
#4200000
0!
04
#4205000
1!
14
b110001111 <
#4210000
0!
04
#4215000
1!
14
b110010000 <
#4220000
0!
04
#4225000
1!
14
b110010001 <
#4230000
0!
04
#4235000
1!
14
b110010010 <
#4240000
0!
04
#4245000
1!
14
b110010011 <
#4250000
0!
04
#4255000
1!
14
b110010100 <
#4260000
0!
04
#4265000
1!
14
b110010101 <
#4270000
0!
04
#4275000
1!
14
b110010110 <
#4280000
0!
04
#4285000
1!
14
b110010111 <
#4290000
0!
04
#4295000
1!
14
b110011000 <
#4300000
0!
04
#4305000
1!
14
b110011001 <
#4310000
0!
04
#4315000
1!
14
b110011010 <
#4320000
0!
04
#4325000
1!
14
b110011011 <
#4330000
0!
04
#4335000
1!
14
b110011100 <
#4340000
0!
04
#4345000
1!
14
b110011101 <
#4350000
0!
04
#4355000
1!
14
b110011110 <
#4360000
0!
04
#4365000
1!
14
b110011111 <
#4370000
0!
04
#4375000
1!
14
b110100000 <
#4380000
0!
04
#4385000
1!
14
b110100001 <
#4390000
0!
04
#4395000
1!
14
b110100010 <
#4400000
0!
04
#4405000
1!
14
b110100011 <
#4410000
0!
04
#4415000
1!
14
b110100100 <
#4420000
0!
04
#4425000
1!
14
b110100101 <
#4430000
0!
04
#4435000
1!
14
b110100110 <
#4440000
0!
04
#4445000
1!
14
b110100111 <
#4450000
0!
04
#4455000
1!
14
b110101000 <
#4460000
0!
04
#4465000
1!
14
b110101001 <
#4470000
0!
04
#4475000
1!
14
b110101010 <
#4480000
0!
04
#4485000
1!
14
b110101011 <
#4490000
0!
04
#4495000
1!
14
b110101100 <
#4500000
0!
04
#4505000
1!
14
b110101101 <
#4510000
0!
04
#4515000
1!
14
b110101110 <
#4520000
0!
04
#4525000
1!
14
b110101111 <
#4530000
0!
04
#4535000
1!
14
b110110000 <
#4540000
0!
04
#4545000
1!
14
b110110001 <
#4550000
0!
04
#4555000
1!
14
b110110010 <
#4560000
0!
04
#4565000
1!
14
b110110011 <
#4570000
0!
04
#4575000
1!
14
b110110100 <
#4580000
0!
04
#4585000
1!
14
b110110101 <
#4590000
0!
04
#4595000
1!
14
b110110110 <
#4600000
0!
04
#4605000
1!
14
b110110111 <
#4610000
0!
04
#4615000
1!
14
b110111000 <
#4620000
0!
04
#4625000
1!
14
b110111001 <
#4630000
0!
04
#4635000
1!
14
b110111010 <
#4640000
0!
04
#4645000
1!
14
b110111011 <
#4650000
0!
04
#4655000
1!
14
b110111100 <
#4660000
0!
04
#4665000
1!
14
b110111101 <
#4670000
0!
04
#4675000
1!
14
b110111110 <
#4680000
0!
04
#4685000
1!
14
b110111111 <
#4690000
0!
04
#4695000
1!
14
b111000000 <
#4700000
0!
04
#4705000
1!
14
b111000001 <
#4710000
0!
04
#4715000
1!
14
b111000010 <
#4720000
0!
04
#4725000
1!
14
b111000011 <
#4730000
0!
04
#4735000
1!
14
b111000100 <
#4740000
0!
04
#4745000
1!
14
b111000101 <
#4750000
0!
04
#4755000
1!
14
b111000110 <
#4760000
0!
04
#4765000
1!
14
b111000111 <
#4770000
0!
04
#4775000
1!
14
b111001000 <
#4780000
0!
04
#4785000
1!
14
b111001001 <
#4790000
0!
04
#4795000
1!
14
b111001010 <
#4800000
0!
04
#4805000
1!
14
b111001011 <
#4810000
0!
04
#4815000
1!
14
b111001100 <
#4820000
0!
04
#4825000
1!
14
b111001101 <
