Semester_5/SIFO/SIFO_Lab_3/src/wire_hz.v
module wire_hz 
#(
    parameter DATA_WIDTH = 8
)
(
    input [DATA_WIDTH-1:0] in_data,
    input out_is_active,
    output tri [DATA_WIDTH-1:0] out_data
);
tri [DATA_WIDTH-1:0] temp_out;

assign temp_out = out_is_active ? in_data : 'bz;
assign out_data = temp_out;

endmodule

Semester_5/SIFO/SIFO_Lab_3/src/ROM.v
module ROM #(
    parameter ADDRESS_WIDTH = 5,
    parameter DATA_WIDTH = 8
)
(
    input clk,
    input [ADDRESS_WIDTH-1:0] address,
    output [DATA_WIDTH-1:0] out_data
);

localparam DATA_DEPTH = 2 ** ADDRESS_WIDTH;

reg [DATA_WIDTH-1:0] memory [DATA_DEPTH-1:0];

integer i;

initial begin
    memory[0] = 1'b1;
    for (i = 1; i < DATA_DEPTH; i = i + 1) begin
        memory[i] = memory[i-1] + 1'b1;
    end
end

assign out_data = memory[address];

endmodule

Semester_5/SIFO/SIFO_Lab_3/src/RAM.v
module RAM #(
    parameter ADDRESS_WIDTH = 5,
    parameter DATA_WIDTH = 8
)
(
    input clk,
    input [ADDRESS_WIDTH-1:0] address,
    input [DATA_WIDTH-1:0] in_data,
    output [DATA_WIDTH-1:0] out_data,
    input write_enable
);

localparam  DATA_DEPTH = 2 ** ADDRESS_WIDTH;

reg [DATA_WIDTH-1:0] memory [DATA_DEPTH-1:0];

integer i;
initial begin
    for(i = 0; i < DATA_DEPTH; i = i + 1) begin
        memory[i] = 3;
    end
    memory[21] = 10;
end

always @(posedge clk) begin
    if(write_enable)  
        memory[address] <= in_data;
end

assign out_data = memory[address];

endmodule

Semester_5/SIFO/SIFO_Lab_3/src/buffer.v
//`include "../src/wire_hz.v"
module buffer #(
    parameter DATA_WIDTH = 8,
    parameter BUFFER_LENGTH = 5
)
(
    input clk,
    input [DATA_WIDTH-1:0] in_data,
    output [DATA_WIDTH-1:0] out_data,
    input do_shift
);

reg [DATA_WIDTH-1:0] shifter [BUFFER_LENGTH-1:0];
//wire [DATA_WIDTH-1:0] temp_data;

integer i;
initial begin
    for(i = 0; i < BUFFER_LENGTH; i = i + 1) begin
        shifter[i] = 0;
    end
end

always @(posedge clk) begin
    if(do_shift) begin
        shifter[0] <= in_data;
        for (i = 1; i < BUFFER_LENGTH; i = i + 1) begin
            shifter[i] <= shifter[i-1];
        end
        //shifter[4:0] <= {shifter[3:0], in_data}; 
        // [2,1,0] <= [1,0] + ['in_data']
    end
    /*if(write_out) begin
        shifter[0] <= 0;
        for (i = 1; i < BUFFER_LENGTH; i = i + 1) begin
            shifter[i] <= shifter[i-1];
        end
        //shifter[BUFFER_LENGTH-1:0] <= {shifter[BUFFER_LENGTH-2:0], 0}; 
        // [2,1,0] <= [1,0] + ['0']
    end*/
end

assign out_data = shifter[BUFFER_LENGTH-1];

/*assign temp_data = shifter[BUFFER_LENGTH-1];

wire_hz wire_hz_1(
    .in_data(temp_data),
    .out_data(out_data),
    .out_is_active(write_out)
);*/

endmodule

Semester_5/SIFO/SIFO_Lab_3/src/all_blocks.v
`include "../src/RAM.v"
`include "../src/ROM.v"
`include "../src/wire_hz.v"
`include "../src/buffer.v"

module all_blocks #(
    parameter ADDRESS_WIDTH = 5,
    parameter DATA_WIDTH = 8,
    parameter BUFFER_LENGTH = 5,
    parameter DATA_DELAY = 3
)(
    input clk,
    input start,
    input rom_nram,
    input [ADDRESS_WIDTH-1:0] address,
	output tri [DATA_WIDTH-1:0] out_data
);
tri [DATA_WIDTH-1:0] general_data_bus;
tri [DATA_WIDTH-1:0] out_ram, out_rom, out_buffer, in_ram, in_buffer;

reg do_shift;
reg [3:0] active_memory_wire;
reg [1:0] active_memory_decode; //00 - none, 01 - rom, 10 - buf, 11 - ram
reg [ADDRESS_WIDTH-1:0] address_counter;
reg [2:0] read_write_counter; 
reg [1:0] delay_counter;

localparam [2:0] start_st = 0, read_st = 1, delay_st = 2, write_st = 3, calm_st = 4;
reg [2:0] current_state;//, next_state;

initial begin
    {active_memory_decode, address_counter,
    read_write_counter, delay_counter, do_shift} = 'bx;
    current_state = calm_st;
end

buffer #(
    .BUFFER_LENGTH(BUFFER_LENGTH), 
    .DATA_WIDTH(DATA_WIDTH)
) buffer_1(
    .clk(clk),
    //.in_data(general_data_bus),
    //.out_data(general_data_bus),
    .in_data(in_buffer),
	.out_data(out_buffer),
    .do_shift(do_shift)
);

RAM #(
    .ADDRESS_WIDTH(ADDRESS_WIDTH),
    .DATA_WIDTH(DATA_WIDTH)
) RAM_1(
    .clk(clk),
    .address(address_counter),
    //.in_data(general_data_bus),
    //.out_data(general_data_bus),
	.in_data(in_ram),
    .out_data(out_ram),
    .write_enable(active_memory_wire[2])
);

ROM #(
    .ADDRESS_WIDTH(ADDRESS_WIDTH),
    .DATA_WIDTH(DATA_WIDTH)
) ROM_1(
    .clk(clk),
    .address(address_counter),
    //.out_data(general_data_bus)
	.out_data(out_rom)
);

wire_hz #(
    .DATA_WIDTH(DATA_WIDTH)
) wire_hz_out_buffer(
    .in_data(out_buffer),
    .out_data(general_data_bus),
    .out_is_active(active_memory_wire[2])
);

wire_hz #(
    .DATA_WIDTH(DATA_WIDTH)
) wire_hz_out_ram(
    .in_data(out_ram),
    .out_data(general_data_bus),
    .out_is_active(active_memory_wire[3])
);

wire_hz #(
    .DATA_WIDTH(DATA_WIDTH)
) wire_hz_out_rom(
    .in_data(out_rom),
    .out_data(general_data_bus),
    .out_is_active(active_memory_wire[1])
);

wire_hz #(
    .DATA_WIDTH(DATA_WIDTH)
) wire_hz_in_buffer(
    .in_data(general_data_bus),
    .out_data(in_buffer),
    .out_is_active(active_memory_wire[1] | active_memory_wire[3]) // buf input is active when rom/ram out is active
);

wire_hz #(
    .DATA_WIDTH(DATA_WIDTH)
) wire_hz_in_ram(
    .in_data(general_data_bus),
    .out_data(in_ram),
    .out_is_active(active_memory_wire[2]) // ram input is active when buf out is active
);

assign out_data = general_data_bus;

always @(*) begin
    case(active_memory_decode)
        2'b00: active_memory_wire = 4'b0001; // none
        2'b01: active_memory_wire = 4'b0010; // rom
        2'b10: active_memory_wire = 4'b0100; // buf
        2'b11: active_memory_wire = 4'b1000; // ram
    endcase
end

always @(posedge clk) begin

    case(current_state) 
    start_st: begin
        address_counter <= address;
        if(rom_nram)
            active_memory_decode <= 2'b01; // rom out is active
        else active_memory_decode <= 2'b11; // ram out it active
        do_shift <= 1;
        read_write_counter <= 0;
        delay_counter <= 0;
        current_state <= read_st;
    end
    read_st: begin
        do_shift <= 1;
        address_counter <= address_counter + 1'b1;
        read_write_counter <= read_write_counter + 1'b1;
        if(read_write_counter == BUFFER_LENGTH - 1) begin
            active_memory_decode <= 2'b00;
            do_shift <= 0;
            current_state <= delay_st;
            read_write_counter <= 0;
        end
    end
    delay_st: begin
        do_shift <= 0;
        delay_counter <= delay_counter + 1'b1;
        address_counter <= address;
        active_memory_decode <= 2'b10;
        if(delay_counter + 1'b1 == DATA_DELAY - 1) begin
            do_shift <= 1;
            current_state <= write_st;
        end
    end
    write_st: begin
        do_shift <= 1;
        address_counter <= address_counter + 1'b1;
        read_write_counter <= read_write_counter + 1'b1;
        if(read_write_counter == BUFFER_LENGTH - 1) begin
            do_shift <= 0;
            current_state <= calm_st;
            active_memory_decode <= 2'b00;
        end
    end
    calm_st: begin
        if(start) current_state <= start_st;
        else current_state <= calm_st;
    end
    endcase
end

// always @(posedge clk) begin
//     current_state <= next_state;

//     case(current_state) 
//     start_st: begin
//         address_counter <= address;
//         if(rom_nram)
//             active_memory_decode <= 2'b01; // rom out is active
//         else active_memory_decode <= 2'b11; // ram out it active
//         do_shift <= 0;
//         read_write_counter <= 0;
//         delay_counter <= 0;
//         next_state <= read_st;
//     end
//     read_st: begin
//         do_shift <= 1;
//         address_counter <= address_counter + 1'b1;
//         read_write_counter <= read_write_counter + 1'b1;
//         if(read_write_counter == BUFFER_LENGTH) begin
//             do_shift <= 0;
//             next_state <= delay_st;
//             read_write_counter <= 0;
//             active_memory_decode <= 2'b10;
//         end
//     end
//     delay_st: begin
//         do_shift <= 0;
//         delay_counter <= delay_counter + 1'b1;
//         if(delay_counter + 1'b1 == DATA_DELAY) begin
//             next_state <= write_st;
//             address_counter <= address;
//         end
//     end
//     write_st: begin
//         do_shift <= 1;
//         address_counter <= address_counter + 1'b1;
//         read_write_counter <= read_write_counter + 1'b1;
//         if(read_write_counter == BUFFER_LENGTH) begin
//             next_state <= calm_st;
//             active_memory_decode <= 2'b00;
//         end
//     end
//     calm_st: begin
//         if(start) next_state <= start_st;
//         else next_state <= calm_st;
//     end
//     endcase
// end

endmodule

Semester_5/SIFO/SIFO_Lab_3/src_testbenches/all_blocks_testbench.v
`include "../src/all_blocks.v"
`timescale 1ns/1ps
module all_blocks_testbench;

parameter ADDRESS_WIDTH = 5;
parameter DATA_WIDTH = 8;
parameter BUFFER_LENGTH = 5;
parameter DATA_DELAY = 3;

reg clk;
reg start;
reg [ADDRESS_WIDTH-1:0] address;
reg rom_nram;
wire [DATA_WIDTH-1:0] general_data_bus;

integer i;

all_blocks #(
    .ADDRESS_WIDTH(ADDRESS_WIDTH),
    .DATA_WIDTH(DATA_WIDTH),
    .DATA_DELAY(DATA_DELAY),
    .BUFFER_LENGTH(BUFFER_LENGTH)
) boje (
    .clk(clk),
    .address(address),
    .start(start),
    .out_data(general_data_bus),
    .rom_nram(rom_nram)
);

always #5 clk = ~clk;

integer fd_mem, fd_monitor;
initial begin : main

    
    fd_mem = $fopen("all_blocks_contains.txt", "w");
    fd_monitor = $fopen("all_blocks_monitor.txt", "w");
    $dumpfile("all_blocks_testbench.vcd");
    $dumpvars;

    $fwrite(fd_mem, "ROM initialization:\n");
    for(i = 0; i < 2**ADDRESS_WIDTH; i = i + 1) begin
        $fwrite(fd_mem, "[%d]", boje.ROM_1.memory[i]);
        if((i + 1) % 8 == 0) begin
            $fwrite(fd_mem, "\n");
        end
    end
    $fwrite(fd_mem, "RAM initialization:\n");
    for(i = 0; i < 2**ADDRESS_WIDTH; i = i + 1) begin
        $fwrite(fd_mem, "[%d]", boje.RAM_1.memory[i]);
        if((i + 1) % 8 == 0) begin
            $fwrite(fd_mem, "\n");
        end
    end

    {clk, start, address, rom_nram} = 0;

//ROM TO RAM START

    #33  
    start = 1;
    address = 0;
    rom_nram = 1;
    #5 start = 0;
	 
    #10 
    address = 16;
    
    #200  

    $fwrite(fd_mem, "\nRAM first time:\n");
    for(i = 0; i < 2**ADDRESS_WIDTH; i = i + 1) begin
        $fwrite(fd_mem, "[%d]", boje.RAM_1.memory[i]);
        if((i + 1) % 8 == 0) begin
            $fwrite(fd_mem, "\n");
        end
    end

//ROM TO RAM ENDS
//RAM TO RAM START

    
    #20  
    address = 17;
    #3
    start = 1;
    rom_nram = 0;
    #5 start = 0;
	 
    #10 
    address = 1;
    
    #200  

    $fwrite(fd_mem, "\nRAM first time:\n");
    for(i = 0; i < 2**ADDRESS_WIDTH; i = i + 1) begin
        $fwrite(fd_mem, "[%d]", boje.RAM_1.memory[i]);
        if((i + 1) % 8 == 0) begin
            $fwrite(fd_mem, "\n");
        end
    end

//RAM TO RAM ENDS

    $fclose(fd_mem);
    $fclose(fd_monitor);
    #20
    $stop;
    $finish;
end

always @(posedge clk) begin
    $fwrite(fd_monitor, "Time:%3d, addres_counter=%d, state=%d, rw_counter=%d, active=%b, do_shift=%d, buf=", 
    $time, boje.address_counter, boje.current_state, boje.read_write_counter, 
    boje.active_memory_decode, boje.do_shift);
    for(i = 0; i< BUFFER_LENGTH; i = i + 1) begin
        $fwrite(fd_monitor, "%d", boje.buffer_1.shifter[i]);
    end
    $fwrite(fd_monitor, "\n");
end

endmodule

Semester_5/SIFO/SIFO_Lab_3/simulation/modelsim/all_blocks_testbench.vcd
$date
	Wed Nov  2 20:42:53 2022
$end
$version
	Questa Intel Starter FPGA Edition Version 2021.2
$end
$timescale
	1ps
$end

$scope module all_blocks_testbench $end
$var parameter 32 ! ADDRESS_WIDTH $end
$var parameter 32 " DATA_WIDTH $end
$var parameter 32 # BUFFER_LENGTH $end
$var parameter 32 $ DATA_DELAY $end
$var reg 1 % clk $end
$var reg 1 & start $end
$var reg 5 ' address [4:0] $end
$var reg 1 ( rom_nram $end
$var wire 1 ) general_data_bus [7] $end
$var wire 1 * general_data_bus [6] $end
$var wire 1 + general_data_bus [5] $end
$var wire 1 , general_data_bus [4] $end
$var wire 1 - general_data_bus [3] $end
$var wire 1 . general_data_bus [2] $end
$var wire 1 / general_data_bus [1] $end
$var wire 1 0 general_data_bus [0] $end
$var integer 32 1 i $end
$var integer 32 2 fd_mem $end
$var integer 32 3 fd_monitor $end

$scope begin main $end
$upscope $end

$scope module boje $end
$var parameter 32 4 ADDRESS_WIDTH $end
$var parameter 32 5 DATA_WIDTH $end
$var parameter 32 6 BUFFER_LENGTH $end
$var parameter 32 7 DATA_DELAY $end
$var parameter 3 8 start_st $end
$var parameter 3 9 read_st $end
$var parameter 3 : delay_st $end
$var parameter 3 ; write_st $end
$var parameter 3 < calm_st $end
$var wire 1 = clk $end
$var wire 1 > start $end
$var wire 1 ? rom_nram $end
$var wire 1 @ address [4] $end
$var wire 1 A address [3] $end
$var wire 1 B address [2] $end
$var wire 1 C address [1] $end
$var wire 1 D address [0] $end
$var tri 1 ) out_data [7] $end
$var tri 1 * out_data [6] $end
$var tri 1 + out_data [5] $end
$var tri 1 , out_data [4] $end
$var tri 1 - out_data [3] $end
$var tri 1 . out_data [2] $end
$var tri 1 / out_data [1] $end
$var tri 1 0 out_data [0] $end
$var tri 1 E general_data_bus [7] $end
$var tri 1 F general_data_bus [6] $end
$var tri 1 G general_data_bus [5] $end
$var tri 1 H general_data_bus [4] $end
$var tri 1 I general_data_bus [3] $end
$var tri 1 J general_data_bus [2] $end
$var tri 1 K general_data_bus [1] $end
$var tri 1 L general_data_bus [0] $end
$var tri 1 M out_ram [7] $end
$var tri 1 N out_ram [6] $end
$var tri 1 O out_ram [5] $end
$var tri 1 P out_ram [4] $end
$var tri 1 Q out_ram [3] $end
$var tri 1 R out_ram [2] $end
$var tri 1 S out_ram [1] $end
$var tri 1 T out_ram [0] $end
$var tri 1 U out_rom [7] $end
$var tri 1 V out_rom [6] $end
$var tri 1 W out_rom [5] $end
$var tri 1 X out_rom [4] $end
$var tri 1 Y out_rom [3] $end
$var tri 1 Z out_rom [2] $end
$var tri 1 [ out_rom [1] $end
$var tri 1 \ out_rom [0] $end
$var tri 1 ] out_buffer [7] $end
$var tri 1 ^ out_buffer [6] $end
$var tri 1 _ out_buffer [5] $end
$var tri 1 ` out_buffer [4] $end
$var tri 1 a out_buffer [3] $end
$var tri 1 b out_buffer [2] $end
$var tri 1 c out_buffer [1] $end
$var tri 1 d out_buffer [0] $end
$var tri 1 e in_ram [7] $end
$var tri 1 f in_ram [6] $end
$var tri 1 g in_ram [5] $end
$var tri 1 h in_ram [4] $end
$var tri 1 i in_ram [3] $end
$var tri 1 j in_ram [2] $end
$var tri 1 k in_ram [1] $end
$var tri 1 l in_ram [0] $end
$var tri 1 m in_buffer [7] $end
$var tri 1 n in_buffer [6] $end
$var tri 1 o in_buffer [5] $end
$var tri 1 p in_buffer [4] $end
$var tri 1 q in_buffer [3] $end
$var tri 1 r in_buffer [2] $end
$var tri 1 s in_buffer [1] $end
$var tri 1 t in_buffer [0] $end
$var reg 1 u do_shift $end
$var reg 4 v active_memory_wire [3:0] $end
$var reg 2 w active_memory_decode [1:0] $end
$var reg 5 x address_counter [4:0] $end
$var reg 3 y read_write_counter [2:0] $end
$var reg 2 z delay_counter [1:0] $end
$var reg 3 { current_state [2:0] $end

$scope module buffer_1 $end
$var parameter 32 | DATA_WIDTH $end
$var parameter 32 } BUFFER_LENGTH $end
$var wire 1 = clk $end
$var wire 1 m in_data [7] $end
$var wire 1 n in_data [6] $end
$var wire 1 o in_data [5] $end
$var wire 1 p in_data [4] $end
$var wire 1 q in_data [3] $end
$var wire 1 r in_data [2] $end
$var wire 1 s in_data [1] $end
$var wire 1 t in_data [0] $end
$var wire 1 ] out_data [7] $end
$var wire 1 ^ out_data [6] $end
$var wire 1 _ out_data [5] $end
$var wire 1 ` out_data [4] $end
$var wire 1 a out_data [3] $end
$var wire 1 b out_data [2] $end
$var wire 1 c out_data [1] $end
$var wire 1 d out_data [0] $end
$var wire 1 ~ do_shift $end
$var integer 32 !! i $end
$upscope $end

$scope module RAM_1 $end
$var parameter 32 "! ADDRESS_WIDTH $end
$var parameter 32 #! DATA_WIDTH $end
$var parameter 32 $! DATA_DEPTH $end
$var wire 1 = clk $end
$var wire 1 %! address [4] $end
$var wire 1 &! address [3] $end
$var wire 1 '! address [2] $end
$var wire 1 (! address [1] $end
$var wire 1 )! address [0] $end
$var wire 1 e in_data [7] $end
$var wire 1 f in_data [6] $end
$var wire 1 g in_data [5] $end
$var wire 1 h in_data [4] $end
$var wire 1 i in_data [3] $end
$var wire 1 j in_data [2] $end
$var wire 1 k in_data [1] $end
$var wire 1 l in_data [0] $end
$var wire 1 M out_data [7] $end
$var wire 1 N out_data [6] $end
$var wire 1 O out_data [5] $end
$var wire 1 P out_data [4] $end
$var wire 1 Q out_data [3] $end
$var wire 1 R out_data [2] $end
$var wire 1 S out_data [1] $end
$var wire 1 T out_data [0] $end
$var wire 1 *! write_enable $end
$var integer 32 +! i $end
$upscope $end

$scope module ROM_1 $end
$var parameter 32 ,! ADDRESS_WIDTH $end
$var parameter 32 -! DATA_WIDTH $end
$var parameter 32 .! DATA_DEPTH $end
$var wire 1 = clk $end
$var wire 1 /! address [4] $end
$var wire 1 0! address [3] $end
$var wire 1 1! address [2] $end
$var wire 1 2! address [1] $end
$var wire 1 3! address [0] $end
$var wire 1 U out_data [7] $end
$var wire 1 V out_data [6] $end
$var wire 1 W out_data [5] $end
$var wire 1 X out_data [4] $end
$var wire 1 Y out_data [3] $end
$var wire 1 Z out_data [2] $end
$var wire 1 [ out_data [1] $end
$var wire 1 \ out_data [0] $end
$var integer 32 4! i $end
$upscope $end

$scope module wire_hz_out_buffer $end
$var parameter 32 5! DATA_WIDTH $end
$var wire 1 ] in_data [7] $end
$var wire 1 ^ in_data [6] $end
$var wire 1 _ in_data [5] $end
$var wire 1 ` in_data [4] $end
$var wire 1 a in_data [3] $end
$var wire 1 b in_data [2] $end
$var wire 1 c in_data [1] $end
$var wire 1 d in_data [0] $end
$var wire 1 6! out_is_active $end
$var tri 1 E out_data [7] $end
$var tri 1 F out_data [6] $end
$var tri 1 G out_data [5] $end
$var tri 1 H out_data [4] $end
$var tri 1 I out_data [3] $end
$var tri 1 J out_data [2] $end
$var tri 1 K out_data [1] $end
$var tri 1 L out_data [0] $end
$var tri 1 7! temp_out [7] $end
$var tri 1 8! temp_out [6] $end
$var tri 1 9! temp_out [5] $end
$var tri 1 :! temp_out [4] $end
$var tri 1 ;! temp_out [3] $end
$var tri 1 <! temp_out [2] $end
$var tri 1 =! temp_out [1] $end
$var tri 1 >! temp_out [0] $end
$upscope $end

$scope module wire_hz_out_ram $end
$var parameter 32 ?! DATA_WIDTH $end
$var wire 1 M in_data [7] $end
$var wire 1 N in_data [6] $end
$var wire 1 O in_data [5] $end
$var wire 1 P in_data [4] $end
$var wire 1 Q in_data [3] $end
$var wire 1 R in_data [2] $end
$var wire 1 S in_data [1] $end
$var wire 1 T in_data [0] $end
$var wire 1 @! out_is_active $end
$var tri 1 E out_data [7] $end
$var tri 1 F out_data [6] $end
$var tri 1 G out_data [5] $end
$var tri 1 H out_data [4] $end
$var tri 1 I out_data [3] $end
$var tri 1 J out_data [2] $end
$var tri 1 K out_data [1] $end
$var tri 1 L out_data [0] $end
$var tri 1 A! temp_out [7] $end
$var tri 1 B! temp_out [6] $end
$var tri 1 C! temp_out [5] $end
$var tri 1 D! temp_out [4] $end
$var tri 1 E! temp_out [3] $end
$var tri 1 F! temp_out [2] $end
$var tri 1 G! temp_out [1] $end
$var tri 1 H! temp_out [0] $end
$upscope $end

$scope module wire_hz_out_rom $end
$var parameter 32 I! DATA_WIDTH $end
$var wire 1 U in_data [7] $end
$var wire 1 V in_data [6] $end
$var wire 1 W in_data [5] $end
$var wire 1 X in_data [4] $end
$var wire 1 Y in_data [3] $end
$var wire 1 Z in_data [2] $end
$var wire 1 [ in_data [1] $end
$var wire 1 \ in_data [0] $end
$var wire 1 J! out_is_active $end
$var tri 1 E out_data [7] $end
$var tri 1 F out_data [6] $end
$var tri 1 G out_data [5] $end
$var tri 1 H out_data [4] $end
$var tri 1 I out_data [3] $end
$var tri 1 J out_data [2] $end
$var tri 1 K out_data [1] $end
$var tri 1 L out_data [0] $end
$var tri 1 K! temp_out [7] $end
$var tri 1 L! temp_out [6] $end
$var tri 1 M! temp_out [5] $end
$var tri 1 N! temp_out [4] $end
$var tri 1 O! temp_out [3] $end
$var tri 1 P! temp_out [2] $end
$var tri 1 Q! temp_out [1] $end
$var tri 1 R! temp_out [0] $end
$upscope $end

$scope module wire_hz_in_buffer $end
$var parameter 32 S! DATA_WIDTH $end
$var wire 1 E in_data [7] $end
$var wire 1 F in_data [6] $end
$var wire 1 G in_data [5] $end
$var wire 1 H in_data [4] $end
$var wire 1 I in_data [3] $end
$var wire 1 J in_data [2] $end
$var wire 1 K in_data [1] $end
$var wire 1 L in_data [0] $end
$var wire 1 T! out_is_active $end
$var tri 1 m out_data [7] $end
$var tri 1 n out_data [6] $end
$var tri 1 o out_data [5] $end
$var tri 1 p out_data [4] $end
$var tri 1 q out_data [3] $end
$var tri 1 r out_data [2] $end
$var tri 1 s out_data [1] $end
$var tri 1 t out_data [0] $end
$var tri 1 U! temp_out [7] $end
$var tri 1 V! temp_out [6] $end
$var tri 1 W! temp_out [5] $end
$var tri 1 X! temp_out [4] $end
$var tri 1 Y! temp_out [3] $end
$var tri 1 Z! temp_out [2] $end
$var tri 1 [! temp_out [1] $end
$var tri 1 \! temp_out [0] $end
$upscope $end

$scope module wire_hz_in_ram $end
$var parameter 32 ]! DATA_WIDTH $end
$var wire 1 E in_data [7] $end
$var wire 1 F in_data [6] $end
$var wire 1 G in_data [5] $end
$var wire 1 H in_data [4] $end
$var wire 1 I in_data [3] $end
$var wire 1 J in_data [2] $end
$var wire 1 K in_data [1] $end
$var wire 1 L in_data [0] $end
$var wire 1 ^! out_is_active $end
$var tri 1 e out_data [7] $end
$var tri 1 f out_data [6] $end
$var tri 1 g out_data [5] $end
$var tri 1 h out_data [4] $end
$var tri 1 i out_data [3] $end
$var tri 1 j out_data [2] $end
$var tri 1 k out_data [1] $end
$var tri 1 l out_data [0] $end
$var tri 1 _! temp_out [7] $end
$var tri 1 `! temp_out [6] $end
$var tri 1 a! temp_out [5] $end
$var tri 1 b! temp_out [4] $end
$var tri 1 c! temp_out [3] $end
$var tri 1 d! temp_out [2] $end
$var tri 1 e! temp_out [1] $end
$var tri 1 f! temp_out [0] $end
$upscope $end
$upscope $end
$upscope $end
$enddefinitions $end
#0
$dumpvars
0%
0&
b0 '
0(
xu
bx v
bx w
bx x
bx y
bx z
b100 {
b101 !
b1000 "
b101 #
b11 $
b101 4
b1000 5
b101 6
b11 7
b0 8
b1 9
b10 :
b11 ;
b100 <
b1000 |
b101 }
b101 "!
b1000 #!
b100000 $!
b101 ,!
b1000 -!
b100000 .!
b1000 5!
b1000 ?!
b1000 I!
b1000 S!
b1000 ]!
b100000 1
b101 !!
b100000 +!
b100000 4!
b10000000000000000000000000000011 2
b10000000000000000000000000000100 3
x0
x/
x.
x-
x,
x+
x*
x)
xL
xK
xJ
xI
xH
xG
xF
xE
xT
xS
xR
xQ
xP
xO
xN
xM
x\
x[
xZ
xY
xX
xW
xV
xU
0d
0c
0b
0a
0`
0_
0^
0]
xl
xk
xj
xi
xh
xg
xf
xe
xt
xs
xr
xq
xp
xo
xn
xm
x>!
x=!
x<!
x;!
x:!
x9!
x8!
x7!
xH!
xG!
xF!
xE!
xD!
xC!
xB!
xA!
xR!
xQ!
xP!
xO!
xN!
xM!
xL!
xK!
x\!
x[!
xZ!
xY!
xX!
xW!
xV!
xU!
xf!
xe!
xd!
xc!
xb!
xa!
x`!
x_!
0D
0C
0B
0A
0@
0?
0>
0=
x^!
xT!
xJ!
x@!
x6!
x3!
x2!
x1!
x0!
x/!
x*!
x)!
x(!
x'!
x&!
x%!
x~
$end
#5000
1%
1=
b0 1
b1 1
b10 1
b11 1
b100 1
b101 1
#10000
0%
0=
#15000
1%
1=
b0 1
b1 1
b10 1
b11 1
b100 1
b101 1
#20000
0%
0=
#25000
1%
1=
b0 1
b1 1
b10 1
b11 1
b100 1
b101 1
#30000
0%
0=
#33000
1&
1(
1>
1?
#35000
1%
1=
b0 1
b1 1
b10 1
b11 1
b100 1
b101 1
b0 {
#38000
0&
0>
#40000
0%
0=
#45000
1%
1=
b0 1
b1 1
b10 1
b11 1
b100 1
b101 1
b0 x
b1 w
1u
b0 y
b0 z
b1 {
03!
02!
01!
00!
0/!
0)!
0(!
0'!
0&!
0%!
1~
0T
0S
0R
0Q
0P
0O
0N
0M
1\
0[
0Z
0Y
0X
0W
0V
0U
b10 v
0@!
0^!
06!
0*!
1T!
1J!
1R!
0Q!
0P!
0O!
0N!
0M!
0L!
0K!
z>!
z=!
z<!
z;!
z:!
z9!
z8!
z7!
zf!
ze!
zd!
zc!
zb!
za!
z`!
z_!
zH!
zG!
zF!
zE!
zD!
zC!
zB!
zA!
1L
0K
0J
0I
0H
0G
0F
0E
zl
zk
zj
zi
zh
zg
zf
ze
1\!
0[!
0Z!
0Y!
0X!
0W!
0V!
0U!
10
0/
0.
0-
0,
0+
0*
0)
1t
0s
0r
0q
0p
0o
0n
0m
#48000
b10000 '
1@
#50000
0%
0=
#55000
1%
1=
b1 !!
b10 !!
b11 !!
b100 !!
b101 !!
b0 1
b1 1
b10 1
b11 1
b100 1
b101 1
b1 x
b1 y
13!
1)!
0\
1[
0R!
1Q!
0L
1K
0\!
1[!
00
1/
0t
1s
#60000
0%
0=
#65000
1%
1=
b1 !!
b10 !!
b11 !!
b100 !!
b101 !!
b0 1
b1 1
b10 1
b11 1
b100 1
b101 1
b10 x
b10 y
03!
12!
0)!
1(!
1\
1R!
1L
1\!
10
1t
#70000
0%
0=
#75000
1%
1=
b1 !!
b10 !!
b11 !!
b100 !!
b101 !!
b0 1
b1 1
b10 1
b11 1
b100 1
b101 1
b11 x
b11 y
13!
1)!
0\
0[
1Z
0R!
0Q!
1P!
0L
0K
1J
0\!
0[!
1Z!
00
0/
1.
0t
0s
1r
#80000
0%
0=
#85000
1%
1=
b1 !!
b10 !!
b11 !!
b100 !!
b101 !!
b0 1
b1 1
b10 1
b11 1
b100 1
b101 1
b100 x
b100 y
03!
02!
11!
0)!
0(!
1'!
1\
1R!
1L
1\!
10
1t
#90000
0%
0=
#95000
1%
1=
b1 !!
b10 !!
b11 !!
b100 !!
b101 !!
b0 1
b1 1
b10 1
b11 1
b100 1
b101 1
b101 x
b101 y
b0 w
0u
b10 {
b0 y
13!
1)!
1d
0~
0\
1[
0R!
1Q!
0L
1K
0\!
1[!
00
1/
0t
1s
b1 v
0T!
0J!
zR!
zQ!
zP!
zO!
zN!
zM!
zL!
zK!
z\!
z[!
zZ!
zY!
zX!
zW!
zV!
zU!
zt
zs
zr
zq
zp
zo
zn
zm
zL
zK
zJ
zI
zH
zG
zF
zE
z0
z/
z.
z-
z,
z+
z*
z)
#100000
0%
0=
#105000
1%
1=
b0 1
b1 1
b10 1
b11 1
b100 1
b101 1
b1 z
b10000 x
b10 w
03!
01!
1/!
0)!
0'!
1%!
1\
0[
0Z
1X
b100 v
1^!
16!
1*!
1>!
0=!
0<!
0;!
0:!
09!
08!
07!
1L
0K
0J
0I
0H
0G
0F
0E
1f!
0e!
0d!
0c!
0b!
0a!
0`!
0_!
10
0/
0.
0-
0,
0+
0*
0)
1l
0k
0j
0i
0h
0g
0f
0e
#110000
0%
0=
#115000
1%
1=
b0 1
b1 1
b10 1
b11 1
b100 1
b101 1
b10 z
1u
b11 {
1T
1~
#120000
0%
0=
#125000
1%
1=
b1 !!
b10 !!
b11 !!
b100 !!
b101 !!
b0 1
b1 1
b10 1
b11 1
b100 1
b101 1
b10001 x
b1 y
13!
1)!
0d
1c
0T
0>!
1=!
0\
1[
0L
1K
0f!
1e!
00
1/
0l
1k
#130000
0%
0=
#135000
1%
1=
b1 !!
b10 !!
b11 !!
b100 !!
b101 !!
b0 1
b1 1
b10 1
b11 1
b100 1
b101 1
b10010 x
b10 y
1d
03!
12!
0)!
1(!
1S
0S
1\
1>!
1L
1f!
10
1l
#140000
0%
0=
#145000
1%
1=
b1 !!
b10 !!
b11 !!
b100 !!
b101 !!
b0 1
b1 1
b10 1
b11 1
b100 1
b101 1
b10011 x
b11 y
1T
1S
13!
1)!
0d
0c
1b
0T
0S
0>!
0=!
1<!
0\
0[
1Z
0L
0K
1J
0f!
0e!
1d!
00
0/
1.
0l
0k
1j
#150000
0%
0=
#155000
1%
1=
b1 !!
b10 !!
b11 !!
b100 !!
b101 !!
b0 1
b1 1
b10 1
b11 1
b100 1
b101 1
b10100 x
b100 y
1d
03!
02!
11!
0)!
0(!
1'!
1R
0R
1\
1>!
1L
1f!
10
1l
#160000
0%
0=
