Semester_5/SIFO/SIFO_Lab_3/src/wire_hz.v
module wire_hz 
#(
    parameter DATA_WIDTH = 8
)
(
    input [DATA_WIDTH-1:0] in_data,
    input out_is_active,
    output tri [DATA_WIDTH-1:0] out_data
);
tri [DATA_WIDTH-1:0] temp_out;

assign temp_out = out_is_active ? in_data : 'bz;
assign out_data = temp_out;

endmodule

Semester_5/SIFO/SIFO_Lab_3/src/buffer.v
//`include "../src/wire_hz.v"
module buffer #(
    parameter DATA_WIDTH = 8,
    parameter BUFFER_LENGTH = 5
)
(
    input clk,
    input [DATA_WIDTH-1:0] in_data,
    output [DATA_WIDTH-1:0] out_data,
    input do_shift
);

reg [DATA_WIDTH-1:0] shifter [BUFFER_LENGTH-1:0];
//wire [DATA_WIDTH-1:0] temp_data;

integer i;
initial begin
    for(i = 0; i < BUFFER_LENGTH; i = i + 1) begin
        shifter[i] = 0;
    end
end

always @(posedge clk) begin
    if(do_shift) begin
        shifter[0] <= in_data;
        for (i = 1; i < BUFFER_LENGTH; i = i + 1) begin
            shifter[i] <= shifter[i-1];
        end
        //shifter[4:0] <= {shifter[3:0], in_data}; 
        // [2,1,0] <= [1,0] + ['in_data']
    end
    /*if(write_out) begin
        shifter[0] <= 0;
        for (i = 1; i < BUFFER_LENGTH; i = i + 1) begin
            shifter[i] <= shifter[i-1];
        end
        //shifter[BUFFER_LENGTH-1:0] <= {shifter[BUFFER_LENGTH-2:0], 0}; 
        // [2,1,0] <= [1,0] + ['0']
    end*/
end

assign out_data = shifter[BUFFER_LENGTH-1];

/*assign temp_data = shifter[BUFFER_LENGTH-1];

wire_hz wire_hz_1(
    .in_data(temp_data),
    .out_data(out_data),
    .out_is_active(write_out)
);*/

endmodule

Semester_5/SIFO/SIFO_Lab_3/src_testbenches/buffer_testbench.v
`include "../src/buffer.v"
`timescale 1ns/1ps
module buffer_testbench;

parameter DATA_WIDTH = 8;
parameter BUFFER_LENGTH = 5;

reg clk;
reg [DATA_WIDTH-1:0] in_data;
wire [DATA_WIDTH-1:0] out_data;
reg do_shift;

integer i;

buffer #(.DATA_WIDTH(DATA_WIDTH), .BUFFER_LENGTH(BUFFER_LENGTH)) dut (
    .clk(clk),
    .in_data(in_data),
    .out_data(out_data),
    .do_shift(do_shift)
);

always #5 clk = ~clk;

initial begin : main
    
    integer fd;
    fd = $fopen("buffer_contains.txt", "w");

    $dumpfile("buffer_testbench.vcd");
    $dumpvars;

    {clk, do_shift} = 0;
    in_data = 'hz;

    repeat(2) @(posedge clk);
    do_shift = #5 1;

    for (i = 0; i < BUFFER_LENGTH; i = i + 1) begin
        repeat(1) @(posedge clk) begin
            in_data = i * 3;
        end
    end

    repeat(1) @(posedge clk);
    in_data = 'hz;
	do_shift = 0;

    for(i = 0; i < BUFFER_LENGTH; i = i + 1) begin
        $fwrite(fd, "[%d]", dut.shifter[i]);
        if((i + 1) % 8 == 0) begin
            $fwrite(fd, "\n");
        end
    end
    $fclose(fd);

    repeat(2) @(posedge clk);
    do_shift = 1;

    repeat(BUFFER_LENGTH) @(posedge clk);
    #20

    $finish;
end
    
endmodule

Semester_5/SIFO/SIFO_Lab_3/simulation/modelsim/buffer_testbench.vcd
$date
	Wed Oct 26 14:37:41 2022
$end
$version
	Questa Intel Starter FPGA Edition Version 2021.2
$end
$timescale
	1ps
$end

$scope module buffer_testbench $end
$var parameter 32 ! DATA_WIDTH $end
$var parameter 32 " BUFFER_LENGTH $end
$var reg 1 # clk $end
$var reg 8 $ in_data [7:0] $end
$var wire 1 % out_data [7] $end
$var wire 1 & out_data [6] $end
$var wire 1 ' out_data [5] $end
$var wire 1 ( out_data [4] $end
$var wire 1 ) out_data [3] $end
$var wire 1 * out_data [2] $end
$var wire 1 + out_data [1] $end
$var wire 1 , out_data [0] $end
$var reg 1 - do_shift $end
$var integer 32 . i $end

$scope begin main $end
$var integer 32 / fd $end
$upscope $end

$scope module dut $end
$var parameter 32 0 DATA_WIDTH $end
$var parameter 32 1 BUFFER_LENGTH $end
$var wire 1 2 clk $end
$var wire 1 3 in_data [7] $end
$var wire 1 4 in_data [6] $end
$var wire 1 5 in_data [5] $end
$var wire 1 6 in_data [4] $end
$var wire 1 7 in_data [3] $end
$var wire 1 8 in_data [2] $end
$var wire 1 9 in_data [1] $end
$var wire 1 : in_data [0] $end
$var wire 1 % out_data [7] $end
$var wire 1 & out_data [6] $end
$var wire 1 ' out_data [5] $end
$var wire 1 ( out_data [4] $end
$var wire 1 ) out_data [3] $end
$var wire 1 * out_data [2] $end
$var wire 1 + out_data [1] $end
$var wire 1 , out_data [0] $end
$var wire 1 ; do_shift $end
$var integer 32 < i $end
$upscope $end
$upscope $end
$enddefinitions $end
#0
$dumpvars
0#
bz $
0-
b1000 !
b101 "
b1000 0
b101 1
bx .
b101 <
b10000000000000000000000000000011 /
0,
0+
0*
0)
0(
0'
0&
0%
0;
z:
z9
z8
z7
z6
z5
z4
z3
02
$end
#5000
1#
12
#10000
0#
02
#15000
1#
12
#20000
0#
1-
b0 .
1;
02
#25000
1#
12
b1 <
b10 <
b11 <
b100 <
b101 <
b0 $
b1 .
0:
09
08
07
06
05
04
03
#30000
0#
02
#35000
1#
12
b1 <
b10 <
b11 <
b100 <
b101 <
b11 $
b10 .
1:
19
#40000
0#
02
#45000
1#
12
b1 <
b10 <
b11 <
b100 <
b101 <
b110 $
b11 .
0:
18
#50000
0#
02
#55000
1#
12
b1 <
b10 <
b11 <
b100 <
b101 <
b1001 $
b100 .
1:
09
08
17
#60000
0#
02
#65000
1#
12
b1 <
b10 <
b11 <
b100 <
b101 <
b1100 $
b101 .
0:
18
z,
z+
z*
z)
z(
z'
z&
z%
#70000
0#
02
#75000
1#
12
b1 <
b10 <
b11 <
b100 <
b101 <
bz $
0-
b0 .
b1 .
b10 .
b11 .
b100 .
b101 .
z:
z9
z8
z7
z6
z5
z4
z3
0;
0,
0+
0*
0)
0(
0'
0&
0%
#80000
0#
02
#85000
1#
12
#90000
0#
02
#95000
1#
12
1-
1;
#100000
0#
02
#105000
1#
12
b1 <
b10 <
b11 <
b100 <
b101 <
1,
1+
#110000
0#
02
#115000
1#
12
b1 <
b10 <
b11 <
b100 <
b101 <
0,
1*
#120000
0#
02
#125000
1#
12
b1 <
b10 <
b11 <
b100 <
b101 <
1,
0+
0*
1)
#130000
0#
02
#135000
1#
12
b1 <
b10 <
b11 <
b100 <
b101 <
0,
1*
#140000
0#
02
#145000
1#
12
b1 <
b10 <
b11 <
b100 <
b101 <
z,
z+
z*
z)
z(
z'
z&
z%
#150000
0#
02
#155000
1#
12
b1 <
b10 <
b11 <
b100 <
b101 <
