Semester_5/SIFO/SIFO_Lab_3/src/RAM.v
module RAM #(
    parameter ADDRESS_WIDTH = 5,
    parameter DATA_WIDTH = 8
)
(
    input clk,
    input [ADDRESS_WIDTH-1:0] address,
    input [DATA_WIDTH-1:0] in_data,
    output [DATA_WIDTH-1:0] out_data,
    input write_enable
);

localparam  DATA_DEPTH = 2 ** ADDRESS_WIDTH;

reg [DATA_WIDTH-1:0] memory [DATA_DEPTH-1:0];

integer i;
initial begin
    for(i = 0; i < DATA_DEPTH; i = i + 1) begin
        memory[i] = 3;
    end
    memory[21] = 10;
end

always @(posedge clk) begin
    if(write_enable)  
        memory[address] <= in_data;
end

assign out_data = memory[address];

endmodule

Semester_5/SIFO/SIFO_Lab_4/src_testbenches/RAM_testbench.v
`include "../src/RAM.v"
`timescale 1ns/1ps
module RAM_testbench;

parameter ADDRESS_WIDTH = 5;
parameter DATA_WIDTH = 8;
parameter DATA_DEPTH = 2 ** ADDRESS_WIDTH;

reg clk;
reg write_enable;
reg [ADDRESS_WIDTH-1:0] address;
reg [DATA_WIDTH-1:0] in_data;
wire [DATA_WIDTH-1:0] out_data;

integer i;

RAM #(.ADDRESS_WIDTH(ADDRESS_WIDTH)) dut (
    .clk(clk),
    .address(address),
    .in_data(in_data),
    .out_data(out_data),
    .write_enable(write_enable)
);

always #5 clk = ~clk;

initial begin : main

    integer fd;
    fd = $fopen("RAM_contains_que.txt", "w");

    $dumpfile("RAM_testbench.vcd");
    $dumpvars;

    {clk, write_enable, in_data, address, i} = 0;

    #20 write_enable = 1;

    for(i = 0; i < 2**ADDRESS_WIDTH; i = i + 1) begin
        repeat(1) @(posedge clk) begin
            address = address + 1;
            in_data = i * 3;
        end
    end

    for(i = 0; i < 2**ADDRESS_WIDTH; i = i + 1) begin
        $fwrite(fd, "[%d]", dut.memory[i]);
        if((i + 1) % 8 == 0) begin
            $fwrite(fd, "\n");
        end
    end
    $fclose(fd);
    
    i = 0;
    write_enable = 0;
    repeat (2) @(posedge clk);

    for(i = 0; i < 2**ADDRESS_WIDTH; i = i + 1) begin
        repeat (1) @(posedge clk) begin
            address = address + 1;
        end
    end

    #20
	$stop;
    $finish;
end

endmodule

Semester_5/SIFO/SIFO_Lab_3/simulation/modelsim/RAM_testbench.vcd
$date
	Wed Oct 26 14:31:41 2022
$end
$version
	Questa Intel Starter FPGA Edition Version 2021.2
$end
$timescale
	1ps
$end

$scope module RAM_testbench $end
$var parameter 32 ! ADDRESS_WIDTH $end
$var parameter 32 " DATA_WIDTH $end
$var parameter 32 # DATA_DEPTH $end
$var reg 1 $ clk $end
$var reg 1 % write_enable $end
$var reg 5 & address [4:0] $end
$var reg 8 ' in_data [7:0] $end
$var wire 1 ( out_data [7] $end
$var wire 1 ) out_data [6] $end
$var wire 1 * out_data [5] $end
$var wire 1 + out_data [4] $end
$var wire 1 , out_data [3] $end
$var wire 1 - out_data [2] $end
$var wire 1 . out_data [1] $end
$var wire 1 / out_data [0] $end
$var integer 32 0 i $end

$scope begin main $end
$var integer 32 1 fd $end
$upscope $end

$scope module dut $end
$var parameter 32 2 ADDRESS_WIDTH $end
$var parameter 32 3 DATA_WIDTH $end
$var parameter 32 4 DATA_DEPTH $end
$var wire 1 5 clk $end
$var wire 1 6 address [4] $end
$var wire 1 7 address [3] $end
$var wire 1 8 address [2] $end
$var wire 1 9 address [1] $end
$var wire 1 : address [0] $end
$var wire 1 ; in_data [7] $end
$var wire 1 < in_data [6] $end
$var wire 1 = in_data [5] $end
$var wire 1 > in_data [4] $end
$var wire 1 ? in_data [3] $end
$var wire 1 @ in_data [2] $end
$var wire 1 A in_data [1] $end
$var wire 1 B in_data [0] $end
$var wire 1 ( out_data [7] $end
$var wire 1 ) out_data [6] $end
$var wire 1 * out_data [5] $end
$var wire 1 + out_data [4] $end
$var wire 1 , out_data [3] $end
$var wire 1 - out_data [2] $end
$var wire 1 . out_data [1] $end
$var wire 1 / out_data [0] $end
$var wire 1 C write_enable $end
$var integer 32 D i $end
$upscope $end
$upscope $end
$enddefinitions $end
#0
$dumpvars
0$
0%
b0 &
b0 '
b101 !
b1000 "
b100000 #
b101 2
b1000 3
b100000 4
b0 0
b100000 D
b10000000000000000000000000000011 1
0/
0.
0-
0,
0+
0*
0)
0(
0C
0B
0A
0@
0?
0>
0=
0<
0;
0:
09
08
07
06
05
$end
#5000
1$
15
#10000
0$
05
#15000
1$
15
#20000
1%
0$
1C
05
#25000
1$
15
b1 &
b1 0
1:
#30000
0$
05
#35000
1$
15
b10 &
b11 '
b10 0
1B
1A
0:
19
#40000
0$
05
#45000
1$
15
b11 &
b110 '
b11 0
0B
1@
1:
#50000
0$
05
#55000
1$
15
b100 &
b1001 '
b100 0
1B
0A
0@
1?
0:
09
18
#60000
0$
05
#65000
1$
15
b101 &
b1100 '
b101 0
0B
1@
1:
#70000
0$
05
#75000
1$
15
b110 &
b1111 '
b110 0
1B
1A
0:
19
#80000
0$
05
#85000
1$
15
b111 &
b10010 '
b111 0
0B
0@
0?
1>
1:
#90000
0$
05
#95000
1$
15
b1000 &
b10101 '
b1000 0
1B
0A
1@
0:
09
08
17
#100000
0$
05
#105000
1$
15
b1001 &
b11000 '
b1001 0
0B
0@
1?
1:
#110000
0$
05
#115000
1$
15
b1010 &
b11011 '
b1010 0
1B
1A
0:
19
#120000
0$
05
#125000
1$
15
b1011 &
b11110 '
b1011 0
0B
1@
1:
#130000
0$
05
#135000
1$
15
b1100 &
b100001 '
b1100 0
1B
0A
0@
0?
0>
1=
0:
09
18
#140000
0$
05
#145000
1$
15
b1101 &
b100100 '
b1101 0
0B
1@
1:
#150000
0$
05
#155000
1$
15
b1110 &
b100111 '
b1110 0
1B
1A
0:
19
#160000
0$
05
#165000
1$
15
b1111 &
b101010 '
b1111 0
0B
0@
1?
1:
#170000
0$
05
#175000
1$
15
b10000 &
b101101 '
b10000 0
1B
0A
1@
0:
09
08
07
16
#180000
0$
05
#185000
1$
15
b10001 &
b110000 '
b10001 0
0B
0@
0?
1>
1:
#190000
0$
05
#195000
1$
15
b10010 &
b110011 '
b10010 0
1B
1A
0:
19
#200000
0$
05
#205000
1$
15
b10011 &
b110110 '
b10011 0
0B
1@
1:
#210000
0$
05
#215000
1$
15
b10100 &
b111001 '
b10100 0
1B
0A
0@
1?
0:
09
18
#220000
0$
05
#225000
1$
15
b10101 &
b111100 '
b10101 0
0B
1@
1:
#230000
0$
05
#235000
1$
15
b10110 &
b111111 '
b10110 0
1B
1A
0:
19
#240000
0$
05
#245000
1$
15
b10111 &
b1000010 '
b10111 0
0B
0@
0?
0>
0=
1<
1:
#250000
0$
05
#255000
1$
15
b11000 &
b1000101 '
b11000 0
1B
0A
1@
0:
09
08
17
#260000
0$
05
#265000
1$
15
b11001 &
b1001000 '
b11001 0
0B
0@
1?
1:
#270000
0$
05
#275000
1$
15
b11010 &
b1001011 '
b11010 0
1B
1A
0:
19
#280000
0$
05
#285000
1$
15
b11011 &
b1001110 '
b11011 0
0B
1@
1:
#290000
0$
05
#295000
1$
15
b11100 &
b1010001 '
b11100 0
1B
0A
0@
0?
1>
0:
09
18
#300000
0$
05
#305000
1$
15
b11101 &
b1010100 '
b11101 0
0B
1@
1:
#310000
0$
05
#315000
1$
15
b11110 &
b1010111 '
b11110 0
1B
1A
0:
19
#320000
0$
05
#325000
1$
15
b11111 &
b1011010 '
b11111 0
0B
0@
1?
1:
#330000
0$
05
#335000
1$
15
b0 &
b1011101 '
b100000 0
b0 0
b1 0
b10 0
b11 0
b100 0
b101 0
b110 0
b111 0
b1000 0
b1001 0
b1010 0
b1011 0
b1100 0
b1101 0
b1110 0
b1111 0
b10000 0
b10001 0
b10010 0
b10011 0
b10100 0
b10101 0
b10110 0
b10111 0
b11000 0
b11001 0
b11010 0
b11011 0
b11100 0
b11101 0
b11110 0
b11111 0
b100000 0
b0 0
0%
1B
0A
1@
0:
09
08
07
06
0C
#340000
0$
05
#345000
1$
15
#350000
0$
05
#355000
1$
15
#360000
0$
05
#365000
1$
15
b1 &
b1 0
1:
#370000
0$
05
#375000
1$
15
b10 &
b10 0
0:
19
1/
1.
#380000
0$
05
#385000
1$
15
b11 &
b11 0
1:
0/
1-
#390000
0$
05
#395000
1$
15
b100 &
b100 0
0:
09
18
1/
0.
0-
1,
#400000
0$
05
#405000
1$
15
b101 &
b101 0
1:
0/
1-
#410000
0$
05
#415000
1$
15
b110 &
b110 0
0:
19
1/
1.
#420000
0$
05
#425000
1$
15
b111 &
b111 0
1:
0/
0-
0,
1+
#430000
0$
05
#435000
1$
15
b1000 &
b1000 0
0:
09
08
17
1/
0.
1-
#440000
0$
05
#445000
1$
15
b1001 &
b1001 0
1:
0/
0-
1,
#450000
0$
05
#455000
1$
15
b1010 &
b1010 0
0:
19
1/
1.
#460000
0$
05
#465000
1$
15
b1011 &
b1011 0
1:
0/
1-
#470000
0$
05
#475000
1$
15
b1100 &
b1100 0
0:
09
18
1/
0.
0-
0,
0+
1*
#480000
0$
05
#485000
1$
15
b1101 &
b1101 0
1:
0/
1-
#490000
0$
05
#495000
1$
15
b1110 &
b1110 0
0:
19
1/
1.
#500000
0$
05
#505000
1$
15
b1111 &
b1111 0
1:
0/
0-
1,
#510000
0$
05
#515000
1$
15
b10000 &
b10000 0
0:
09
08
07
16
1/
0.
1-
#520000
0$
05
#525000
1$
15
b10001 &
b10001 0
1:
0/
0-
0,
1+
#530000
0$
05
#535000
1$
15
b10010 &
b10010 0
0:
19
1/
1.
#540000
0$
05
#545000
1$
15
b10011 &
b10011 0
1:
0/
1-
#550000
0$
05
#555000
1$
15
b10100 &
b10100 0
0:
09
18
1/
0.
0-
1,
#560000
0$
05
#565000
1$
15
b10101 &
b10101 0
1:
0/
1-
#570000
0$
05
#575000
1$
15
b10110 &
b10110 0
0:
19
1/
1.
#580000
0$
05
#585000
1$
15
b10111 &
b10111 0
1:
0/
0-
0,
0+
0*
1)
#590000
0$
05
#595000
1$
15
b11000 &
b11000 0
0:
09
08
17
1/
0.
1-
#600000
0$
05
#605000
1$
15
b11001 &
b11001 0
1:
0/
0-
1,
#610000
0$
05
#615000
1$
15
b11010 &
b11010 0
0:
19
1/
1.
#620000
0$
05
#625000
1$
15
b11011 &
b11011 0
1:
0/
1-
#630000
0$
05
#635000
1$
15
b11100 &
b11100 0
0:
09
18
1/
0.
0-
0,
1+
#640000
0$
05
#645000
1$
15
b11101 &
b11101 0
1:
0/
1-
#650000
0$
05
#655000
1$
15
b11110 &
b11110 0
0:
19
1/
1.
#660000
0$
05
#665000
1$
15
b11111 &
b11111 0
1:
0/
0-
1,
#670000
0$
05
#675000
1$
15
b0 &
b100000 0
0:
09
08
07
06
0.
0,
0+
0)
