Semester_5/SIFO/SIFO_Lab_3/src/ROM.v
module ROM #(
    parameter ADDRESS_WIDTH = 5,
    parameter DATA_WIDTH = 8
)
(
    input clk,
    input [ADDRESS_WIDTH-1:0] address,
    output [DATA_WIDTH-1:0] out_data
);

localparam DATA_DEPTH = 2 ** ADDRESS_WIDTH;

reg [DATA_WIDTH-1:0] memory [DATA_DEPTH-1:0];

integer i;

initial begin
    memory[0] = 1'b1;
    for (i = 1; i < DATA_DEPTH; i = i + 1) begin
        memory[i] = memory[i-1] + 1'b1;
    end
end

assign out_data = memory[address];

endmodule

Semester_5/SIFO/SIFO_Lab_3/src_testbenches/ROM_testbench.v
`include "../src/ROM.v"
`timescale 1ns/1ps
module ROM_testbench;

parameter ADDRESS_WIDTH = 5;
parameter DATA_WIDTH = 8;
localparam DATA_DEPTH = 2 ** ADDRESS_WIDTH;

reg clk;
reg [ADDRESS_WIDTH-1:0] address;
wire [DATA_WIDTH-1:0] out_data;

integer i;

ROM dut (
    .clk(clk),
    .address(address),
    .out_data(out_data)
);

always #5 clk = ~clk;

initial begin : main

    integer fd;
    fd = $fopen("ROM_contains.txt", "w");

    $dumpfile("ROM_testbench.vcd");
    $dumpvars;

    {clk, address} = 0;

    repeat (2) @(posedge clk);

    for(i = 0; i < 2**ADDRESS_WIDTH; i = i + 1) begin
        $fwrite(fd, "[%d]", dut.memory[i]);
        if((i+1) % 8 == 0) begin
            $fwrite(fd, "\n");
        end
    end
    $fclose(fd);

    for(i = 0; i < 2**ADDRESS_WIDTH; i = i + 1) begin
        repeat (1) @(posedge clk) begin
            address = i;
        end
    end

    #20
	$stop;
    $finish;
end

endmodule

Semester_5/SIFO/SIFO_Lab_3/simulation/modelsim/ROM_testbench.vcd
$date
	Fri Oct 21 10:59:56 2022
$end
$version
	Questa Intel Starter FPGA Edition Version 2021.2
$end
$timescale
	1ps
$end

$scope module ROM_testbench $end
$var parameter 32 ! ADDRESS_WIDTH $end
$var parameter 32 " DATA_WIDTH $end
$var parameter 32 # DATA_DEPTH $end
$var reg 1 $ clk $end
$var reg 5 % address [4:0] $end
$var wire 1 & out_data [7] $end
$var wire 1 ' out_data [6] $end
$var wire 1 ( out_data [5] $end
$var wire 1 ) out_data [4] $end
$var wire 1 * out_data [3] $end
$var wire 1 + out_data [2] $end
$var wire 1 , out_data [1] $end
$var wire 1 - out_data [0] $end
$var integer 32 . i $end

$scope begin main $end
$var integer 32 / fd $end
$upscope $end

$scope module dut $end
$var parameter 32 0 ADDRESS_WIDTH $end
$var parameter 32 1 DATA_WIDTH $end
$var parameter 32 2 DATA_DEPTH $end
$var wire 1 3 clk $end
$var wire 1 4 address [4] $end
$var wire 1 5 address [3] $end
$var wire 1 6 address [2] $end
$var wire 1 7 address [1] $end
$var wire 1 8 address [0] $end
$var wire 1 & out_data [7] $end
$var wire 1 ' out_data [6] $end
$var wire 1 ( out_data [5] $end
$var wire 1 ) out_data [4] $end
$var wire 1 * out_data [3] $end
$var wire 1 + out_data [2] $end
$var wire 1 , out_data [1] $end
$var wire 1 - out_data [0] $end
$var integer 32 9 i $end
$upscope $end
$upscope $end
$enddefinitions $end
#0
$dumpvars
0$
b0 %
b101 !
b1000 "
b100000 #
b101 0
b1000 1
b100000 2
bx .
b100000 9
b10000000000000000000000000000011 /
0-
0,
0+
0*
0)
0(
0'
0&
08
07
06
05
04
03
$end
#5000
1$
13
#10000
0$
03
#15000
1$
13
b0 .
b1 .
b10 .
b11 .
b100 .
b101 .
b110 .
b111 .
b1000 .
b1001 .
b1010 .
b1011 .
b1100 .
b1101 .
b1110 .
b1111 .
b10000 .
b10001 .
b10010 .
b10011 .
b10100 .
b10101 .
b10110 .
b10111 .
b11000 .
b11001 .
b11010 .
b11011 .
b11100 .
b11101 .
b11110 .
b11111 .
b100000 .
b0 .
#20000
0$
03
#25000
1$
13
b1 .
#30000
0$
03
#35000
1$
13
b1 %
b10 .
18
1-
#40000
0$
03
#45000
1$
13
b10 %
b11 .
08
17
0-
1,
#50000
0$
03
#55000
1$
13
b11 %
b100 .
18
1-
#60000
0$
03
#65000
1$
13
b100 %
b101 .
08
07
16
0-
0,
1+
#70000
0$
03
#75000
1$
13
b101 %
b110 .
18
1-
#80000
0$
03
#85000
1$
13
b110 %
b111 .
08
17
0-
1,
#90000
0$
03
#95000
1$
13
b111 %
b1000 .
18
1-
#100000
0$
03
#105000
1$
13
b1000 %
b1001 .
08
07
06
15
0-
0,
0+
1*
#110000
0$
03
#115000
1$
13
b1001 %
b1010 .
18
1-
#120000
0$
03
#125000
1$
13
b1010 %
b1011 .
08
17
0-
1,
#130000
0$
03
#135000
1$
13
b1011 %
b1100 .
18
1-
#140000
0$
03
#145000
1$
13
b1100 %
b1101 .
08
07
16
0-
0,
1+
#150000
0$
03
#155000
1$
13
b1101 %
b1110 .
18
1-
#160000
0$
03
#165000
1$
13
b1110 %
b1111 .
08
17
0-
1,
#170000
0$
03
#175000
1$
13
b1111 %
b10000 .
18
1-
#180000
0$
03
#185000
1$
13
b10000 %
b10001 .
08
07
06
05
14
0-
0,
0+
0*
1)
#190000
0$
03
#195000
1$
13
b10001 %
b10010 .
18
1-
#200000
0$
03
#205000
1$
13
b10010 %
b10011 .
08
17
0-
1,
#210000
0$
03
#215000
1$
13
b10011 %
b10100 .
18
1-
#220000
0$
03
#225000
1$
13
b10100 %
b10101 .
08
07
16
0-
0,
1+
#230000
0$
03
#235000
1$
13
b10101 %
b10110 .
18
1-
#240000
0$
03
#245000
1$
13
b10110 %
b10111 .
08
17
0-
1,
#250000
0$
03
#255000
1$
13
b10111 %
b11000 .
18
1-
#260000
0$
03
#265000
1$
13
b11000 %
b11001 .
08
07
06
15
0-
0,
0+
1*
#270000
0$
03
#275000
1$
13
b11001 %
b11010 .
18
1-
#280000
0$
03
#285000
1$
13
b11010 %
b11011 .
08
17
0-
1,
#290000
0$
03
#295000
1$
13
b11011 %
b11100 .
18
1-
#300000
0$
03
#305000
1$
13
b11100 %
b11101 .
08
07
16
0-
0,
1+
#310000
0$
03
#315000
1$
13
b11101 %
b11110 .
18
1-
#320000
0$
03
#325000
1$
13
b11110 %
b11111 .
08
17
0-
1,
#330000
0$
03
#335000
1$
13
b11111 %
b100000 .
18
1-
